Workbook

Sheet 01_Поставщики
A1: Справочник условий Apple-трейдеров — источник КМ от 18.08.2026
A3: Контрагент | B3: Базис поставки | C3: Условия оплаты (договор) | D3: Условия оплаты (факт) | E3: Оплата в валюте | F3: Инвестинг | G3: Комиссии / конвертация | H3: Инспекция | I3: Готовность к инспекции | J3: Срок поставки | K3: Компенсация брака | L3: Комментарий | M3: Источник
A4: Inonics trading LLC | B4: CIP | C4: Отсрочка 30 дней, Предоплата 100%, Предоплата/Отсрочка | D4: По договорённости - предоплата 100%: 80/20; 70/30; 50/50 | E4: НБ РБ - RUB | F4: нет | G4: дополнительно 1% при оплате (наши фин добавляют) | H4: нет | I4: нет | J4: 10-14 дней | K4: да | M4: Файл КМ 18.08.2026
A5: HuaXun Group Limited | B5: CIP | C5: Предоплата 20/Отсрочка 80 (CNY), Предоплата 20/Отсрочка 80 (RUB), Предоплата (CNY), Предоплата (RUB), Предоплата (USD) | D5: 20% предоплата и 80% отсрочка | E5: CNY | F5: нет | G5: нет | H5: нет | I5: нет | J5: 30-60 дней | K5: нет | M5: Файл КМ 18.08.2026
A6: ANGEL TRADE CO., LIMITED | B6: DAP | C6: Предоплата, Предоплата 50%/Отсрочка 50%, Разовая отсрочка | D6: Предоплата 50%/Отсрочка 50% 5 к.д. после прибытия на ПТО | E6: НБ РБ - CNY | F6: да, на дату оплаты *0,5% (проводится только на первый платёж) | G6: 0,5% | H6: нет | I6: нет | J6: 14-30 дней | K6: нет | M6: Файл КМ 18.08.2026
A7: Tech Planet FZCO (ОАЭ) | B7: EXW | C7: Предоплата | D7: Предоплата (частями) - 70%-30%; 80%-20% | E7: ЦБ РФ - RUB | F7: да, на дату оплаты+0,10 центов (проводится на каждый платёж) | G7: 1,5% - комиссия агента за рублёвую оплату | H7: да | I7: 3-7 дней | J7: 14-30 дней | K7: нет | M7: Файл КМ 18.08.2026
A8: Al Shiva General Trading FZE (ОАЭ) | B8: EXW | C8: Предоплата (частями) | D8: Предоплата (частями) - 100%, 70%-30%; 80%-20%; 100% после инспекции | E8: ЦБ РФ - RUB | F8: да, на дату оплаты (проводится на каждый платёж) | G8: 1,5% - агентские | H8: да | I8: 8-10 дней | J8: 14-30 дней | K8: нет | M8: Файл КМ 18.08.2026
A9: Noviva DWC LLC (ОАЭ) | B9: EXW | C9: Предоплата 20%/Отсрочка 80% (RUR), Предоплата (20%/80%) (USD), Отсрочка 115 дн, Предоплата | D9: Предоплата 20% и 80% после инспекции | E9: ЦБ РФ - RUB; AED - фикс курс 3,674 | F9: нет | G9: 1,125% - стоимость конвертации рублей в дирхамы | H9: да | I9: 2-5 дней | J9: 14-30 дней | K9: нет | M9: Файл КМ 18.08.2026
A10: KVN Group FZCO (ОАЭ) - Бигап | B10: EXW | C10: Отсрочка 5 дн, Предоплата 20%/Отсрочка 80% | D10: По договорённости - Предоплата 100% после инспекции; 20/80 | E10: ЦБ РФ - RUB; AED - фикс курс 3,674 | F10: нет | G10: дополнительно 1% при оплате (наши фин добавляют) | H10: да | I10: 2-3 дня | J10: 7-14 дней | K10: нет | M10: Файл КМ 18.08.2026
A11: Metal Market L.L.C-FZ (ОАЭ) | B11: FCA, FOB, EXW, DAP, DAT - условия согласовываются на каждую партию товара | C11: Отсрочка 7 дн. После поступления товара на ПТО | D11: - | E11: ЦБ РФ - RUB | F11: ? | G11: ? | H11: FCA, FOB, EXW - да???; DAP, DAT - нет??? | I11: 5 дней | J11: FCA, FOB, EXW - обязаны забрать в течение 5 к.д. с подтверждения; DAP, DAT - отгрузить в течение 20 к.д. | K11: да | L11: Инфо только по договору - физически не отгружали | M11: Файл КМ 18.08.2026

Sheet 02_Схемы оплаты
A1: Схемы оплаты — шаблоны процентов; фактические даты и курсы задаются в конкретном оффере
A3: Поставщик | B3: Схема | C3: Платёж 1 | D3: Платёж 2 | E3: Платёж 3 | F3: Событие / примечание | G3: Статус | H3: Ключ (служебный)
A4: Inonics trading LLC | B4: 100% | C4: 1 | D4: 0 | E4: 0 | F4: Фактическая дата вручную | G4: по факту | H4: =A4&"|"&B4 -> Inonics trading LLC|100%
A5: Inonics trading LLC | B5: 80/20 | C5: 0.8 | D5: 0.2 | E5: 0 | F5: По договорённости | G5: по факту | H5: =A5&"|"&B5 -> Inonics trading LLC|80/20
A6: Inonics trading LLC | B6: 70/30 | C6: 0.7 | D6: 0.3 | E6: 0 | F6: По договорённости | G6: по факту | H6: =A6&"|"&B6 -> Inonics trading LLC|70/30
A7: Inonics trading LLC | B7: 50/50 | C7: 0.5 | D7: 0.5 | E7: 0 | F7: По договорённости | G7: по факту | H7: =A7&"|"&B7 -> Inonics trading LLC|50/50
A8: HuaXun Group Limited | B8: 20/80 | C8: 0.2 | D8: 0.8 | E8: 0 | F8: 20% предоплата / 80% отсрочка | G8: по факту | H8: =A8&"|"&B8 -> HuaXun Group Limited|20/80
A9: ANGEL TRADE CO., LIMITED | B9: 50/50 | C9: 0.5 | D9: 0.5 | E9: 0 | F9: Вторая часть — 5 к.д. после прибытия на ПТО | G9: по факту | H9: =A9&"|"&B9 -> ANGEL TRADE CO., LIMITED|50/50
A10: Tech Planet FZCO (ОАЭ) | B10: 70/30 | C10: 0.7 | D10: 0.3 | E10: 0 | F10: Предоплата частями | G10: по факту | H10: =A10&"|"&B10 -> Tech Planet FZCO (ОАЭ)|70/30
A11: Tech Planet FZCO (ОАЭ) | B11: 80/20 | C11: 0.8 | D11: 0.2 | E11: 0 | F11: Предоплата частями | G11: по факту | H11: =A11&"|"&B11 -> Tech Planet FZCO (ОАЭ)|80/20
A12: Al Shiva General Trading FZE (ОАЭ) | B12: 100% | C12: 1 | D12: 0 | E12: 0 | F12: Предоплата | G12: по факту | H12: =A12&"|"&B12 -> Al Shiva General Trading FZE (ОАЭ)|100%
A13: Al Shiva General Trading FZE (ОАЭ) | B13: 70/30 | C13: 0.7 | D13: 0.3 | E13: 0 | F13: Предоплата частями | G13: по факту | H13: =A13&"|"&B13 -> Al Shiva General Trading FZE (ОАЭ)|70/30
A14: Al Shiva General Trading FZE (ОАЭ) | B14: 80/20 | C14: 0.8 | D14: 0.2 | E14: 0 | F14: Предоплата частями | G14: по факту | H14: =A14&"|"&B14 -> Al Shiva General Trading FZE (ОАЭ)|80/20
A15: Al Shiva General Trading FZE (ОАЭ) | B15: 100% после инспекции | C15: 1 | D15: 0 | E15: 0 | F15: После инспекции | G15: по факту | H15: =A15&"|"&B15 -> Al Shiva General Trading FZE (ОАЭ)|100% после инспекции
... A19: Metal Market L.L.C-FZ (ОАЭ) | B19: РУЧНАЯ | C19: 0 | D19: 0 | E19: 0 | F19: Условия партии вводятся вручную | G19: не верифицировано | H19: =A19&"|"&B19 -> Metal Market L.L.C-FZ (ОАЭ)|РУЧНАЯ

Sheet 03_Настройки
A1: Настройки модели и справочные курсы
A3: Параметр | B3: Значение | C3: Ед. | D3: Комментарий
A4: Стоимость денег | B4: 0.13 | C4: % годовых | D4: Рабочая ставка из постановки задачи
A5: Допуск суммы долей платежей | B5: 0.001 | C5: доля | D5: Для проверки 100%
A6: Максимальный риск | B6: 100 | C6: 0-100 | D6: Риск пока информационный, не влияет на победителя
A7: Использовать стоимость дефицита | B7: Да | C7: Да/Нет | D7: Глобальный выключатель
A8: Дата расчёта | B8: 46254 | C8: дата
A9: Целевое покрытие спроса, дней | B9: 30 | C9: дней | D9: Для оценки Потребности по факту (остаток+транзит) в 04_Потребность, когда готового плана заказа нет в источнике — можно скорректировать
A11: Валюта | B11: Курс к BYN | C11: Источник | D11: Дата/время курса | E11: Статус | F11: Комментарий
A12: USD | B12: 3.25 | E12: Пример
A13: RUB | B13: 0.0335 | E13: Пример
A14: CNY | B14: 0.365 | E14: Пример
A15: AED | B15: 0.885 | E15: Пример
A16: EUR | E16: Ввести

Sheet 04_Потребность
A1: Потребность тендера — одна строка на Tender ID + SKU
A3: Tender ID | B3: Дата тендера | C3: Наименование / SKU | D3: Потребность, шт | E3: Нужная дата ЦС | F3: Продажи/день, шт | G3: ВП/маржа на ед., BYN | H3: Считать дефицит | I3: Комментарий | J3: Остаток на складе, шт (источник) | K3: Транзит, шт (источник) | L3: Продажи за 15 дней, шт (источник) | M3: Источник данных
D4: 320 | F4: =ROUND(L4/15,1) -> 0
D5: =MAX(0,ROUND(F5*'03_Настройки'!$B$9-J5-K5,0)) -> 0 | F5: =ROUND(L5/15,1) -> 0
D6: =MAX(0,ROUND(F6*'03_Настройки'!$B$9-J6-K6,0)) -> 0 | F6: =ROUND(L6/15,1) -> 0
D7: =MAX(0,ROUND(F7*'03_Настройки'!$B$9-J7-K7,0)) -> 0 | F7: =ROUND(L7/15,1) -> 0
D8: =MAX(0,ROUND(F8*'03_Настройки'!$B$9-J8-K8,0)) -> 0 | F8: =ROUND(L8/15,1) -> 0
D9: =MAX(0,ROUND(F9*'03_Настройки'!$B$9-J9-K9,0)) -> 0 | F9: =ROUND(L9/15,1) -> 0
D10: =MAX(0,ROUND(F10*'03_Настройки'!$B$9-J10-K10,0)) -> 0 | F10: =ROUND(L10/15,1) -> 0
D11: =MAX(0,ROUND(F11*'03_Настройки'!$B$9-J11-K11,0)) -> 0 | F11: =ROUND(L11/15,1) -> 0
D12: =MAX(0,ROUND(F12*'03_Настройки'!$B$9-J12-K12,0)) -> 0 | F12: =ROUND(L12/15,1) -> 0
D13: =MAX(0,ROUND(F13*'03_Настройки'!$B$9-J13-K13,0)) -> 0 | F13: =ROUND(L13/15,1) -> 0

Sheet 05_Офферы
A1: Тендерный калькулятор — офферы и автоматический выбор
A2: ЖЁЛТЫЕ поля — ввод КМ/поставщика. ЗЕЛЁНЫЕ — расчёт. Курс и комиссия задаются по каждому платежу отдельно. Доли платежей (T/X/AB) подтягиваются автоматически по схеме — можно перезаписать вручную. Столбцы BG:BO — SIM/eSIM, страна происхождения, нотификация, сертификат, статус позиции и авто-флаг «Флаг соответствия» (см. 06_Методика).
A3: Tender ID | B3: SKU / Артикул Patio | C3: Поставщик | D3: Доступно, шт | E3: Цена/ед. | F3: Валюта цены | G3: Схема оплаты | H3: Базис (справ.) | I3: Базис факт | J3: Инспекция (справ.) | K3: Оплата факт (справ.) | L3: Срок поставки (справ.) | M3: Дата тендера | N3: ETA ЦС Минск | O3: Ввоз разрешён | P3: Документы подтверждены | Q3: Логистика/ед., BYN | R3: Прочие/ед., BYN | S3: Страхование, % | T3: Платёж1, % | U3: Дата плат.1 | V3: Курс1 к BYN | W3: Комиссия1, % | X3: Платёж2, % | Y3: Дата плат.2 | Z3: Курс2 к BYN | AA3: Комиссия2, % | AB3: Платёж3, % | AC3: Дата плат.3 | AD3: Курс3 к BYN | AE3: Комиссия3, % | AF3: Риск, 0-100 | AG3: Комментарий | AH3: Потребность | AI3: Нужная дата | AJ3: Продажи/день | AK3: Маржа/ед. | AL3: Дефицит вкл. | AM3: Покрытие | AN3: Сумма долей | AO3: Товар/ед., BYN | AP3: Страх./ед. | AQ3: Cash landed/ед. | AR3: Стоимость денег/ед. | AS3: Полная фин. цена/ед. | AT3: Срок, дней | AU3: Опоздание, дней | AV3: Потерянные продажи, шт | AW3: Потери ВП, BYN | AX3: Стоимость закупки, BYN | AY3: Экономическая стоимость, BYN | AZ3: Расчёт допустим | BA3: Полное покрытие | BB3: CHEAPEST | BC3: FASTEST | BD3: OPTIMAL | BE3: Причина / статус | BF3: Row | BG3: SIM, шт | BH3: eSIM, шт | BI3: Страна происхождения | BJ3: Нотификация | BK3: Сертификат/протокол № | BL3: Сертификат действ. до | BM3: Статус позиции | BN3: Проверка SIM/eSIM | BO3: Флаг соответствия | BP3: Комментарий (соответствие) | BQ3: Срок действия оффера, до | BR3: Named place / точка передачи | BS3: Кто организует межд. логистику | BT3: Регион/рынок устройства | BU3: Статус документа соответствия | BV3: Предлагаемый артикул/наименование | BW3: Предлагаемый цвет | BX3: Есть отличие от запроса | BY3: Замена согласована Patio | BZ3: Полнота формы | CA3: Модель / A-number | CB3: Наименование | CC3: Нотификация № / срок
H4: =IFERROR(VLOOKUP(C4,'01_Поставщики'!$A$4:$M$11,2,FALSE()),"") | J4: =IFERROR(VLOOKUP(C4,'01_Поставщики'!$A$4:$M$11,8,FALSE()),"") | K4: =IFERROR(VLOOKUP(C4,'01_Поставщики'!$A$4:$M$11,4,FALSE()),"") | L4: =IFERROR(VLOOKUP(C4,'01_Поставщики'!$A$4:$M$11,10,FALSE()),"") | T4: =IFERROR(INDEX('02_Схемы оплаты'!$C$4:$C$19,MATCH($C4&"|"&$G4,'02_Схемы оплаты'!$H$4:$H$19,0)),0) -> 0 | X4: =IFERROR(INDEX('02_Схемы оплаты'!$D$4:$D$19,MATCH($C4&"|"&$G4,'02_Схемы оплаты'!$H$4:$H$19,0)),0) -> 0 | AB4: =IFERROR(INDEX('02_Схемы оплаты'!$E$4:$E$19,MATCH($C4&"|"&$G4,'02_Схемы оплаты'!$H$4:$H$19,0)),0) -> 0 | AH4: =IFERROR(SUMIFS('04_Потребность'!$D$4:$D$103,'04_Потребность'!$A$4:$A$103,A4,'04_Потребность'!$C$4:$C$103,B4),0) -> 0 | AI4: =IF(OR(A4="",B4=""),"",IFERROR(SUMIFS('04_Потребность'!$E$4:$E$103,'04_Потребность'!$A$4:$A$103,A4,'04_Потребность'!$C$4:$C$103,B4),0)) | AJ4: =IF(OR(A4="",B4=""),"",IFERROR(SUMIFS('04_Потребность'!$F$4:$F$103,'04_Потребность'!$A$4:$A$103,A4,'04_Потребность'!$C$4:$C$103,B4),0)) | AK4: =IF(OR(A4="",B4=""),"",IFERROR(SUMIFS('04_Потребность'!$G$4:$G$103,'04_Потребность'!$A$4:$A$103,A4,'04_Потребность'!$C$4:$C$103,B4),0)) | AL4: =IF('03_Настройки'!$B$7="Нет","Нет",IF(COUNTIFS('04_Потребность'!$A$4:$A$103,A4,'04_Потребность'!$C$4:$C$103,B4,'04_Потребность'!$H$4:$H$103,"Да")>0,"Да","Нет")) -> Нет | AM4: =IFERROR(MIN(1,D4/AH4),0) -> 0 | AN4: =SUM(T4,X4,AB4) -> 0 | AO4: =IFERROR(E4*(T4*V4*(1+W4)+X4*Z4*(1+AA4)+AB4*AD4*(1+AE4)),0) -> 0 | AP4: =AO4*S4 -> 0 | AQ4: =AO4+AP4+Q4+R4 -> 0 | AR4: =IFERROR(E4*'03_Настройки'!$B$4/365*(IF(T4>0,T4*V4*(1+W4)*MAX(0,N4-U4),0)+IF(X4>0,X4*Z4*(1+AA4)*MAX(0,N4-Y4),0)+IF(AB4>0,AB4*AD4*(1+AE4)*MAX(0,N4-AC4),0)),0) -> 0 | AS4: =AQ4+AR4 -> 0 | AT4: =IFERROR(MAX(0,N4-M4),0) -> 0 | AU4: =IFERROR(MAX(0,N4-AI4),0) -> 0 | AV4: =IF(AL4="Да",MIN(AH4,AJ4*AU4),0) -> 0 | AW4: =AV4*AK4 -> #VALUE! | AX4: =AS4*AH4 -> 0 | AY4: =AX4+AW4 -> #VALUE! | AZ4: =IF(AND(A4<>"",B4<>"",C4<>"",D4>0,E4>0,N4<>"",AH4>0,O4="Да",P4="Да",BZ4="ПОЛНО",ABS(AN4-1)<='03_Настройки'!$B$5,IF(T4>0,AND(U4<>"",V4>0),TRUE()),IF(X4>0,AND(Y4<>"",Z4>0),TRUE()),IF(AB4>0,AND(AC4<>"",AD4>0),TRUE()),OR(BM4="",BM4="Активна")),"Да","Нет") -> Нет | BA4: =IF(AM4>=1,"Да","Нет") -> Нет | BB4: =IF(AND(AZ4="Да",BA4="Да",COUNTIFS($A$4:$A$203,A4,$B$4:$B$203,B4,$AZ$4:$AZ$203,"Да",$BA$4:$BA$203,"Да",$AX$4:$AX$203,"<"&AX4)=0,COUNTIFS($A$4:$A$203,A4,$B$4:$B$203,B4,$AZ$4:$AZ$203,"Да",$BA$4:$BA$203,"Да",$AX$4:$AX$203,"="&AX4,$BF$4:$BF$203,"<"&BF4)=0),"ДА","") | BC4: =IF(AND(AZ4="Да",BA4="Да",COUNTIFS($A$4:$A$203,A4,$B$4:$B$203,B4,$AZ$4:$AZ$203,"Да",$BA$4:$BA$203,"Да",$N$4:$N$203,"<"&N4)=0,COUNTIFS($A$4:$A$203,A4,$B$4:$B$203,B4,$AZ$4:$AZ$203,"Да",$BA$4:$BA$203,"Да",$N$4:$N$203,"="&N4,$BF$4:$BF$203,"<"&BF4)=0),"ДА","") | BD4: =IF(AND(AZ4="Да",BA4="Да",COUNTIFS($A$4:$A$203,A4,$B$4:$B$203,B4,$AZ$4:$AZ$203,"Да",$BA$4:$BA$203,"Да",$AY$4:$AY$203,"<"&AY4)=0,COUNTIFS($A$4:$A$203,A4,$B$4:$B$203,B4,$AZ$4:$AZ$203,"Да",$BA$4:$BA$203,"Да",$AY$4:$AY$203,"="&AY4,$BF$4:$BF$203,"<"&BF4)=0),"ДА","") | BE4: =IF(A4="","",IF(BZ4<>"ПОЛНО","BLOCK: неполная форма",IF(O4<>"Да","BLOCK: ввоз не разрешён",IF(P4<>"Да","BLOCK: документы не подтверждены",IF(ABS(AN4-1)>'03_Настройки'!$B$5,"BLOCK: платежи не 100%",IF(AND(BM4<>"",BM4<>"Активна"),"BLOCK: позиция "&BM4,IF(BA4<>"Да","PARTIAL: не покрывает потребность",IF(BB4="ДА","самый дешёвый"&IF(BC4="ДА"," + быстрый","")&IF(BD4="ДА"," + optimal",""),IF(BC4="ДА","самый быстрый"&IF(BD4="ДА"," + optimal",""),IF(BD4="ДА","optimal","Допущен")))))))))) | BF4: =ROW() -> 4 | BN4: =IF(BG4+BH4=0,"",IF(BG4+BH4<>D4,"⚠ SIM+eSIM≠Доступно","OK")) | BO4: =IF($C4="","",IF(TRIM(IF(O4<>"Да","⚠Ввоз ","")&IF(P4<>"Да","⚠Документы ","")&IF(AND(BG4+BH4>0,D4>0,BG4+BH4<>D4),"⚠SIM/eSIM ","")&IF(BZ4<>"ПОЛНО","⚠НеполнаяФорма ",""))="","OK",TRIM(IF(O4<>"Да","⚠Ввоз ","")&IF(P4<>"Да","⚠Документы ","")&IF(AND(BG4+BH4>0,D4>0,BG4+BH4<>D4),"⚠SIM/eSIM ","")&IF(BZ4<>"ПОЛНО","⚠НеполнаяФорма ","")))) | BX4: =IF(OR(BV4<>"",BW4<>""),"Да","") | BZ4: =IF(A4="","",IF(AND(BT4<>"",BJ4<>"",CA4<>"",BK4<>"",OR(BG4<>"",BH4<>""),BM4<>""),"ПОЛНО","НЕПОЛНО"))
H5: =IFERROR(VLOOKUP(C5,'01_Поставщики'!$A$4:$M$11,2,FALSE()),"") | J5: =IFERROR(VLOOKUP(C5,'01_Поставщики'!$A$4:$M$11,8,FALSE()),"") | K5: =IFERROR(VLOOKUP(C5,'01_Поставщики'!$A$4:$M$11,4,FALSE()),"") | L5: =IFERROR(VLOOKUP(C5,'01_Поставщики'!$A$4:$M$11,10,FALSE()),"") | M5: =IF(OR(A5="",B5=""),"",IFERROR(SUMIFS('04_Потребность'!$B$4:$B$103,'04_Потребность'!$A$4:$A$103,A5,'04_Потребность'!$C$4:$C$103,B5),0)) | T5: =IFERROR(INDEX('02_Схемы оплаты'!$C$4:$C$19,MATCH($C5&"|"&$G5,'02_Схемы оплаты'!$H$4:$H$19,0)),0) -> 0 | X5: =IFERROR(INDEX('02_Схемы оплаты'!$D$4:$D$19,MATCH($C5&"|"&$G5,'02_Схемы оплаты'!$H$4:$H$19,0)),0) -> 0 | AB5: =IFERROR(INDEX('02_Схемы оплаты'!$E$4:$E$19,MATCH($C5&"|"&$G5,'02_Схемы оплаты'!$H$4:$H$19,0)),0) -> 0 | AH5: =IFERROR(SUMIFS('04_Потребность'!$D$4:$D$103,'04_Потребность'!$A$4:$A$103,A5,'04_Потребность'!$C$4:$C$103,B5),0) -> 0 | AI5: =IF(OR(A5="",B5=""),"",IFERROR(SUMIFS('04_Потребность'!$E$4:$E$103,'04_Потребность'!$A$4:$A$103,A5,'04_Потребность'!$C$4:$C$103,B5),0)) | AJ5: =IF(OR(A5="",B5=""),"",IFERROR(SUMIFS('04_Потребность'!$F$4:$F$103,'04_Потребность'!$A$4:$A$103,A5,'04_Потребность'!$C$4:$C$103,B5),0)) | AK5: =IF(OR(A5="",B5=""),"",IFERROR(SUMIFS('04_Потребность'!$G$4:$G$103,'04_Потребность'!$A$4:$A$103,A5,'04_Потребность'!$C$4:$C$103,B5),0)) | AL5: =IF('03_Настройки'!$B$7="Нет","Нет",IF(COUNTIFS('04_Потребность'!$A$4:$A$103,A5,'04_Потребность'!$C$4:$C$103,B5,'04_Потребность'!$H$4:$H$103,"Да")>0,"Да","Нет")) -> Нет | AM5: =IFERROR(MIN(1,D5/AH5),0) -> 0 | AN5: =SUM(T5,X5,AB5) -> 0 | AO5: =IFERROR(E5*(T5*V5*(1+W5)+X5*Z5*(1+AA5)+AB5*AD5*(1+AE5)),0) -> 0 | AP5: =AO5*S5 -> 0 | AQ5: =AO5+AP5+Q5+R5 -> 0 | AR5: =IFERROR(E5*'03_Настройки'!$B$4/365*(IF(T5>0,T5*V5*(1+W5)*MAX(0,N5-U5),0)+IF(X5>0,X5*Z5*(1+AA5)*MAX(0,N5-Y5),0)+IF(AB5>0,AB5*AD5*(1+AE5)*MAX(0,N5-AC5),0)),0) -> 0 | AS5: =AQ5+AR5 -> 0 | AT5: =IFERROR(MAX(0,N5-M5),0) -> 0 | AU5: =IFERROR(MAX(0,N5-AI5),0) -> 0 | AV5: =IF(AL5="Да",MIN(AH5,AJ5*AU5),0) -> 0 | AW5: =AV5*AK5 -> #VALUE! | AX5: =AS5*AH5 -> 0 | AY5: =AX5+AW5 -> #VALUE! | AZ5: =IF(AND(A5<>"",B5<>"",C5<>"",D5>0,E5>0,N5<>"",AH5>0,O5="Да",P5="Да",BZ5="ПОЛНО",ABS(AN5-1)<='03_Настройки'!$B$5,IF(T5>0,AND(U5<>"",V5>0),TRUE()),IF(X5>0,AND(Y5<>"",Z5>0),TRUE()),IF(AB5>0,AND(AC5<>"",AD5>0),TRUE()),OR(BM5="",BM5="Активна")),"Да","Нет") -> Нет | BA5: =IF(AM5>=1,"Да","Нет") -> Нет | BB5: =IF(AND(AZ5="Да",BA5="Да",COUNTIFS($A$4:$A$203,A5,$B$4:$B$203,B5,$AZ$4:$AZ$203,"Да",$BA$4:$BA$203,"Да",$AX$4:$AX$203,"<"&AX5)=0,COUNTIFS($A$4:$A$203,A5,$B$4:$B$203,B5,$AZ$4:$AZ$203,"Да",$BA$4:$BA$203,"Да",$AX$4:$AX$203,"="&AX5,$BF$4:$BF$203,"<"&BF5)=0),"ДА","") | BC5: =IF(AND(AZ5="Да",BA5="Да",COUNTIFS($A$4:$A$203,A5,$B$4:$B$203,B5,$AZ$4:$AZ$203,"Да",$BA$4:$BA$203,"Да",$N$4:$N$203,"<"&N5)=0,COUNTIFS($A$4:$A$203,A5,$B$4:$B$203,B5,$AZ$4:$AZ$203,"Да",$BA$4:$BA$203,"Да",$N$4:$N$203,"="&N5,$BF$4:$BF$203,"<"&BF5)=0),"ДА","") | BD5: =IF(AND(AZ5="Да",BA5="Да",COUNTIFS($A$4:$A$203,A5,$B$4:$B$203,B5,$AZ$4:$AZ$203,"Да",$BA$4:$BA$203,"Да",$AY$4:$AY$203,"<"&AY5)=0,COUNTIFS($A$4:$A$203,A5,$B$4:$B$203,B5,$AZ$4:$AZ$203,"Да",$BA$4:$BA$203,"Да",$AY$4:$AY$203,"="&AY5,$BF$4:$BF$203,"<"&BF5)=0),"ДА","") | BE5: =IF(A5="","",IF(BZ5<>"ПОЛНО","BLOCK: неполная форма",IF(O5<>"Да","BLOCK: ввоз не разрешён",IF(P5<>"Да","BLOCK: документы не подтверждены",IF(ABS(AN5-1)>'03_Настройки'!$B$5,"BLOCK: платежи не 100%",IF(AND(BM5<>"",BM5<>"Активна"),"BLOCK: позиция "&BM5,IF(BA5<>"Да","PARTIAL: не покрывает потребность",IF(BB5="ДА","самый дешёвый"&IF(BC5="ДА"," + быстрый","")&IF(BD5="ДА"," + optimal",""),IF(BC5="ДА","самый быстрый"&IF(BD5="ДА"," + optimal",""),IF(BD5="ДА","optimal","Допущен")))))))))) | BF5: =ROW() -> 5 | BN5: =IF(BG5+BH5=0,"",IF(BG5+BH5<>D5,"⚠ SIM+eSIM≠Доступно","OK")) | BO5: =IF($C5="","",IF(TRIM(IF(O5<>"Да","⚠Ввоз ","")&IF(P5<>"Да","⚠Документы ","")&IF(AND(BG5+BH5>0,D5>0,BG5+BH5<>D5),"⚠SIM/eSIM ","")&IF(BZ5<>"ПОЛНО","⚠НеполнаяФорма ",""))="","OK",TRIM(IF(O5<>"Да","⚠Ввоз ","")&IF(P5<>"Да","⚠Документы ","")&IF(AND(BG5+BH5>0,D5>0,BG5+BH5<>D5),"⚠SIM/eSIM ","")&IF(BZ5<>"ПОЛНО","⚠НеполнаяФорма ","")))) | BX5: =IF(OR(BV5<>"",BW5<>""),"Да","") | BZ5: =IF(A5="","",IF(AND(BT5<>"",BJ5<>"",CA5<>"",BK5<>"",OR(BG5<>"",BH5<>""),BM5<>""),"ПОЛНО","НЕПОЛНО"))
H6: =IFERROR(VLOOKUP(C6,'01_Поставщики'!$A$4:$M$11,2,FALSE()),"") | J6: =IFERROR(VLOOKUP(C6,'01_Поставщики'!$A$4:$M$11,8,FALSE()),"") | K6: =IFERROR(VLOOKUP(C6,'01_Поставщики'!$A$4:$M$11,4,FALSE()),"") | L6: =IFERROR(VLOOKUP(C6,'01_Поставщики'!$A$4:$M$11,10,FALSE()),"") | M6: =IF(OR(A6="",B6=""),"",IFERROR(SUMIFS('04_Потребность'!$B$4:$B$103,'04_Потребность'!$A$4:$A$103,A6,'04_Потребность'!$C$4:$C$103,B6),0)) | T6: =IFERROR(INDEX('02_Схемы оплаты'!$C$4:$C$19,MATCH($C6&"|"&$G6,'02_Схемы оплаты'!$H$4:$H$19,0)),0) -> 0 | X6: =IFERROR(INDEX('02_Схемы оплаты'!$D$4:$D$19,MATCH($C6&"|"&$G6,'02_Схемы оплаты'!$H$4:$H$19,0)),0) -> 0 | AB6: =IFERROR(INDEX('02_Схемы оплаты'!$E$4:$E$19,MATCH($C6&"|"&$G6,'02_Схемы оплаты'!$H$4:$H$19,0)),0) -> 0 | AH6: =IFERROR(SUMIFS('04_Потребность'!$D$4:$D$103,'04_Потребность'!$A$4:$A$103,A6,'04_Потребность'!$C$4:$C$103,B6),0) -> 0 | AI6: =IF(OR(A6="",B6=""),"",IFERROR(SUMIFS('04_Потребность'!$E$4:$E$103,'04_Потребность'!$A$4:$A$103,A6,'04_Потребность'!$C$4:$C$103,B6),0)) | AJ6: =IF(OR(A6="",B6=""),"",IFERROR(SUMIFS('04_Потребность'!$F$4:$F$103,'04_Потребность'!$A$4:$A$103,A6,'04_Потребность'!$C$4:$C$103,B6),0)) | AK6: =IF(OR(A6="",B6=""),"",IFERROR(SUMIFS('04_Потребность'!$G$4:$G$103,'04_Потребность'!$A$4:$A$103,A6,'04_Потребность'!$C$4:$C$103,B6),0)) | AL6: =IF('03_Настройки'!$B$7="Нет","Нет",IF(COUNTIFS('04_Потребность'!$A$4:$A$103,A6,'04_Потребность'!$C$4:$C$103,B6,'04_Потребность'!$H$4:$H$103,"Да")>0,"Да","Нет")) -> Нет | AM6: =IFERROR(MIN(1,D6/AH6),0) -> 0 | AN6: =SUM(T6,X6,AB6) -> 0 | AO6: =IFERROR(E6*(T6*V6*(1+W6)+X6*Z6*(1+AA6)+AB6*AD6*(1+AE6)),0) -> 0 | AP6: =AO6*S6 -> 0 | AQ6: =AO6+AP6+Q6+R6 -> 0 | AR6: =IFERROR(E6*'03_Настройки'!$B$4/365*(IF(T6>0,T6*V6*(1+W6)*MAX(0,N6-U6),0)+IF(X6>0,X6*Z6*(1+AA6)*MAX(0,N6-Y6),0)+IF(AB6>0,AB6*AD6*(1+AE6)*MAX(0,N6-AC6),0)),0) -> 0 | AS6: =AQ6+AR6 -> 0 | AT6: =IFERROR(MAX(0,N6-M6),0) -> 0 | AU6: =IFERROR(MAX(0,N6-AI6),0) -> 0 | AV6: =IF(AL6="Да",MIN(AH6,AJ6*AU6),0) -> 0 | AW6: =AV6*AK6 -> #VALUE! | AX6: =AS6*AH6 -> 0 | AY6: =AX6+AW6 -> #VALUE! | AZ6: =IF(AND(A6<>"",B6<>"",C6<>"",D6>0,E6>0,N6<>"",AH6>0,O6="Да",P6="Да",BZ6="ПОЛНО",ABS(AN6-1)<='03_Настройки'!$B$5,IF(T6>0,AND(U6<>"",V6>0),TRUE()),IF(X6>0,AND(Y6<>"",Z6>0),TRUE()),IF(AB6>0,AND(AC6<>"",AD6>0),TRUE()),OR(BM6="",BM6="Активна")),"Да","Нет") -> Нет | BA6: =IF(AM6>=1,"Да","Нет") -> Нет | BB6: =IF(AND(AZ6="Да",BA6="Да",COUNTIFS($A$4:$A$203,A6,$B$4:$B$203,B6,$AZ$4:$AZ$203,"Да",$BA$4:$BA$203,"Да",$AX$4:$AX$203,"<"&AX6)=0,COUNTIFS($A$4:$A$203,A6,$B$4:$B$203,B6,$AZ$4:$AZ$203,"Да",$BA$4:$BA$203,"Да",$AX$4:$AX$203,"="&AX6,$BF$4:$BF$203,"<"&BF6)=0),"ДА","") | BC6: =IF(AND(AZ6="Да",BA6="Да",COUNTIFS($A$4:$A$203,A6,$B$4:$B$203,B6,$AZ$4:$AZ$203,"Да",$BA$4:$BA$203,"Да",$N$4:$N$203,"<"&N6)=0,COUNTIFS($A$4:$A$203,A6,$B$4:$B$203,B6,$AZ$4:$AZ$203,"Да",$BA$4:$BA$203,"Да",$N$4:$N$203,"="&N6,$BF$4:$BF$203,"<"&BF6)=0),"ДА","") | BD6: =IF(AND(AZ6="Да",BA6="Да",COUNTIFS($A$4:$A$203,A6,$B$4:$B$203,B6,$AZ$4:$AZ$203,"Да",$BA$4:$BA$203,"Да",$AY$4:$AY$203,"<"&AY6)=0,COUNTIFS($A$4:$A$203,A6,$B$4:$B$203,B6,$AZ$4:$AZ$203,"Да",$BA$4:$BA$203,"Да",$AY$4:$AY$203,"="&AY6,$BF$4:$BF$203,"<"&BF6)=0),"ДА","") | BE6: =IF(A6="","",IF(BZ6<>"ПОЛНО","BLOCK: неполная форма",IF(O6<>"Да","BLOCK: ввоз не разрешён",IF(P6<>"Да","BLOCK: документы не подтверждены",IF(ABS(AN6-1)>'03_Настройки'!$B$5,"BLOCK: платежи не 100%",IF(AND(BM6<>"",BM6<>"Активна"),"BLOCK: позиция "&BM6,IF(BA6<>"Да","PARTIAL: не покрывает потребность",IF(BB6="ДА","самый дешёвый"&IF(BC6="ДА"," + быстрый","")&IF(BD6="ДА"," + optimal",""),IF(BC6="ДА","самый быстрый"&IF(BD6="ДА"," + optimal",""),IF(BD6="ДА","optimal","Допущен")))))))))) | BF6: =ROW() -> 6 | BN6: =IF(BG6+BH6=0,"",IF(BG6+BH6<>D6,"⚠ SIM+eSIM≠Доступно","OK")) | BO6: =IF($C6="","",IF(TRIM(IF(O6<>"Да","⚠Ввоз ","")&IF(P6<>"Да","⚠Документы ","")&IF(AND(BG6+BH6>0,D6>0,BG6+BH6<>D6),"⚠SIM/eSIM ","")&IF(BZ6<>"ПОЛНО","⚠НеполнаяФорма ",""))="","OK",TRIM(IF(O6<>"Да","⚠Ввоз ","")&IF(P6<>"Да","⚠Документы ","")&IF(AND(BG6+BH6>0,D6>0,BG6+BH6<>D6),"⚠SIM/eSIM ","")&IF(BZ6<>"ПОЛНО","⚠НеполнаяФорма ","")))) | BX6: =IF(OR(BV6<>"",BW6<>""),"Да","") | BZ6: =IF(A6="","",IF(AND(BT6<>"",BJ6<>"",CA6<>"",BK6<>"",OR(BG6<>"",BH6<>""),BM6<>""),"ПОЛНО","НЕПОЛНО"))
H7: =IFERROR(VLOOKUP(C7,'01_Поставщики'!$A$4:$M$11,2,FALSE()),"") | J7: =IFERROR(VLOOKUP(C7,'01_Поставщики'!$A$4:$M$11,8,FALSE()),"") | K7: =IFERROR(VLOOKUP(C7,'01_Поставщики'!$A$4:$M$11,4,FALSE()),"") | L7: =IFERROR(VLOOKUP(C7,'01_Поставщики'!$A$4:$M$11,10,FALSE()),"") | M7: =IF(OR(A7="",B7=""),"",IFERROR(SUMIFS('04_Потребность'!$B$4:$B$103,'04_Потребность'!$A$4:$A$103,A7,'04_Потребность'!$C$4:$C$103,B7),0)) | T7: =IFERROR(INDEX('02_Схемы оплаты'!$C$4:$C$19,MATCH($C7&"|"&$G7,'02_Схемы оплаты'!$H$4:$H$19,0)),0) -> 0 | X7: =IFERROR(INDEX('02_Схемы оплаты'!$D$4:$D$19,MATCH($C7&"|"&$G7,'02_Схемы оплаты'!$H$4:$H$19,0)),0) -> 0 | AB7: =IFERROR(INDEX('02_Схемы оплаты'!$E$4:$E$19,MATCH($C7&"|"&$G7,'02_Схемы оплаты'!$H$4:$H$19,0)),0) -> 0 | AH7: =IFERROR(SUMIFS('04_Потребность'!$D$4:$D$103,'04_Потребность'!$A$4:$A$103,A7,'04_Потребность'!$C$4:$C$103,B7),0) -> 0 | AI7: =IF(OR(A7="",B7=""),"",IFERROR(SUMIFS('04_Потребность'!$E$4:$E$103,'04_Потребность'!$A$4:$A$103,A7,'04_Потребность'!$C$4:$C$103,B7),0)) | AJ7: =IF(OR(A7="",B7=""),"",IFERROR(SUMIFS('04_Потребность'!$F$4:$F$103,'04_Потребность'!$A$4:$A$103,A7,'04_Потребность'!$C$4:$C$103,B7),0)) | AK7: =IF(OR(A7="",B7=""),"",IFERROR(SUMIFS('04_Потребность'!$G$4:$G$103,'04_Потребность'!$A$4:$A$103,A7,'04_Потребность'!$C$4:$C$103,B7),0)) | AL7: =IF('03_Настройки'!$B$7="Нет","Нет",IF(COUNTIFS('04_Потребность'!$A$4:$A$103,A7,'04_Потребность'!$C$4:$C$103,B7,'04_Потребность'!$H$4:$H$103,"Да")>0,"Да","Нет")) -> Нет | AM7: =IFERROR(MIN(1,D7/AH7),0) -> 0 | AN7: =SUM(T7,X7,AB7) -> 0 | AO7: =IFERROR(E7*(T7*V7*(1+W7)+X7*Z7*(1+AA7)+AB7*AD7*(1+AE7)),0) -> 0 | AP7: =AO7*S7 -> 0 | AQ7: =AO7+AP7+Q7+R7 -> 0 | AR7: =IFERROR(E7*'03_Настройки'!$B$4/365*(IF(T7>0,T7*V7*(1+W7)*MAX(0,N7-U7),0)+IF(X7>0,X7*Z7*(1+AA7)*MAX(0,N7-Y7),0)+IF(AB7>0,AB7*AD7*(1+AE7)*MAX(0,N7-AC7),0)),0) -> 0 | AS7: =AQ7+AR7 -> 0 | AT7: =IFERROR(MAX(0,N7-M7),0) -> 0 | AU7: =IFERROR(MAX(0,N7-AI7),0) -> 0 | AV7: =IF(AL7="Да",MIN(AH7,AJ7*AU7),0) -> 0 | AW7: =AV7*AK7 -> #VALUE! | AX7: =AS7*AH7 -> 0 | AY7: =AX7+AW7 -> #VALUE! | AZ7: =IF(AND(A7<>"",B7<>"",C7<>"",D7>0,E7>0,N7<>"",AH7>0,O7="Да",P7="Да",BZ7="ПОЛНО",ABS(AN7-1)<='03_Настройки'!$B$5,IF(T7>0,AND(U7<>"",V7>0),TRUE()),IF(X7>0,AND(Y7<>"",Z7>0),TRUE()),IF(AB7>0,AND(AC7<>"",AD7>0),TRUE()),OR(BM7="",BM7="Активна")),"Да","Нет") -> Нет | BA7: =IF(AM7>=1,"Да","Нет") -> Нет | BB7: =IF(AND(AZ7="Да",BA7="Да",COUNTIFS($A$4:$A$203,A7,$B$4:$B$203,B7,$AZ$4:$AZ$203,"Да",$BA$4:$BA$203,"Да",$AX$4:$AX$203,"<"&AX7)=0,COUNTIFS($A$4:$A$203,A7,$B$4:$B$203,B7,$AZ$4:$AZ$203,"Да",$BA$4:$BA$203,"Да",$AX$4:$AX$203,"="&AX7,$BF$4:$BF$203,"<"&BF7)=0),"ДА","") | BC7: =IF(AND(AZ7="Да",BA7="Да",COUNTIFS($A$4:$A$203,A7,$B$4:$B$203,B7,$AZ$4:$AZ$203,"Да",$BA$4:$BA$203,"Да",$N$4:$N$203,"<"&N7)=0,COUNTIFS($A$4:$A$203,A7,$B$4:$B$203,B7,$AZ$4:$AZ$203,"Да",$BA$4:$BA$203,"Да",$N$4:$N$203,"="&N7,$BF$4:$BF$203,"<"&BF7)=0),"ДА","") | BD7: =IF(AND(AZ7="Да",BA7="Да",COUNTIFS($A$4:$A$203,A7,$B$4:$B$203,B7,$AZ$4:$AZ$203,"Да",$BA$4:$BA$203,"Да",$AY$4:$AY$203,"<"&AY7)=0,COUNTIFS($A$4:$A$203,A7,$B$4:$B$203,B7,$AZ$4:$AZ$203,"Да",$BA$4:$BA$203,"Да",$AY$4:$AY$203,"="&AY7,$BF$4:$BF$203,"<"&BF7)=0),"ДА","") | BE7: =IF(A7="","",IF(BZ7<>"ПОЛНО","BLOCK: неполная форма",IF(O7<>"Да","BLOCK: ввоз не разрешён",IF(P7<>"Да","BLOCK: документы не подтверждены",IF(ABS(AN7-1)>'03_Настройки'!$B$5,"BLOCK: платежи не 100%",IF(AND(BM7<>"",BM7<>"Активна"),"BLOCK: позиция "&BM7,IF(BA7<>"Да","PARTIAL: не покрывает потребность",IF(BB7="ДА","самый дешёвый"&IF(BC7="ДА"," + быстрый","")&IF(BD7="ДА"," + optimal",""),IF(BC7="ДА","самый быстрый"&IF(BD7="ДА"," + optimal",""),IF(BD7="ДА","optimal","Допущен")))))))))) | BF7: =ROW() -> 7 | BN7: =IF(BG7+BH7=0,"",IF(BG7+BH7<>D7,"⚠ SIM+eSIM≠Доступно","OK")) | BO7: =IF($C7="","",IF(TRIM(IF(O7<>"Да","⚠Ввоз ","")&IF(P7<>"Да","⚠Документы ","")&IF(AND(BG7+BH7>0,D7>0,BG7+BH7<>D7),"⚠SIM/eSIM ","")&IF(BZ7<>"ПОЛНО","⚠НеполнаяФорма ",""))="","OK",TRIM(IF(O7<>"Да","⚠Ввоз ","")&IF(P7<>"Да","⚠Документы ","")&IF(AND(BG7+BH7>0,D7>0,BG7+BH7<>D7),"⚠SIM/eSIM ","")&IF(BZ7<>"ПОЛНО","⚠НеполнаяФорма ","")))) | BX7: =IF(OR(BV7<>"",BW7<>""),"Да","") | BZ7: =IF(A7="","",IF(AND(BT7<>"",BJ7<>"",CA7<>"",BK7<>"",OR(BG7<>"",BH7<>""),BM7<>""),"ПОЛНО","НЕПОЛНО"))
H8: =IFERROR(VLOOKUP(C8,'01_Поставщики'!$A$4:$M$11,2,FALSE()),"") | J8: =IFERROR(VLOOKUP(C8,'01_Поставщики'!$A$4:$M$11,8,FALSE()),"") | K8: =IFERROR(VLOOKUP(C8,'01_Поставщики'!$A$4:$M$11,4,FALSE()),"") | L8: =IFERROR(VLOOKUP(C8,'01_Поставщики'!$A$4:$M$11,10,FALSE()),"") | M8: =IF(OR(A8="",B8=""),"",IFERROR(SUMIFS('04_Потребность'!$B$4:$B$103,'04_Потребность'!$A$4:$A$103,A8,'04_Потребность'!$C$4:$C$103,B8),0)) | T8: =IFERROR(INDEX('02_Схемы оплаты'!$C$4:$C$19,MATCH($C8&"|"&$G8,'02_Схемы оплаты'!$H$4:$H$19,0)),0) -> 0 | X8: =IFERROR(INDEX('02_Схемы оплаты'!$D$4:$D$19,MATCH($C8&"|"&$G8,'02_Схемы оплаты'!$H$4:$H$19,0)),0) -> 0 | AB8: =IFERROR(INDEX('02_Схемы оплаты'!$E$4:$E$19,MATCH($C8&"|"&$G8,'02_Схемы оплаты'!$H$4:$H$19,0)),0) -> 0 | AH8: =IFERROR(SUMIFS('04_Потребность'!$D$4:$D$103,'04_Потребность'!$A$4:$A$103,A8,'04_Потребность'!$C$4:$C$103,B8),0) -> 0 | AI8: =IF(OR(A8="",B8=""),"",IFERROR(SUMIFS('04_Потребность'!$E$4:$E$103,'04_Потребность'!$A$4:$A$103,A8,'04_Потребность'!$C$4:$C$103,B8),0)) | AJ8: =IF(OR(A8="",B8=""),"",IFERROR(SUMIFS('04_Потребность'!$F$4:$F$103,'04_Потребность'!$A$4:$A$103,A8,'04_Потребность'!$C$4:$C$103,B8),0)) | AK8: =IF(OR(A8="",B8=""),"",IFERROR(SUMIFS('04_Потребность'!$G$4:$G$103,'04_Потребность'!$A$4:$A$103,A8,'04_Потребность'!$C$4:$C$103,B8),0)) | AL8: =IF('03_Настройки'!$B$7="Нет","Нет",IF(COUNTIFS('04_Потребность'!$A$4:$A$103,A8,'04_Потребность'!$C$4:$C$103,B8,'04_Потребность'!$H$4:$H$103,"Да")>0,"Да","Нет")) -> Нет | AM8: =IFERROR(MIN(1,D8/AH8),0) -> 0 | AN8: =SUM(T8,X8,AB8) -> 0 | AO8: =IFERROR(E8*(T8*V8*(1+W8)+X8*Z8*(1+AA8)+AB8*AD8*(1+AE8)),0) -> 0 | AP8: =AO8*S8 -> 0 | AQ8: =AO8+AP8+Q8+R8 -> 0 | AR8: =IFERROR(E8*'03_Настройки'!$B$4/365*(IF(T8>0,T8*V8*(1+W8)*MAX(0,N8-U8),0)+IF(X8>0,X8*Z8*(1+AA8)*MAX(0,N8-Y8),0)+IF(AB8>0,AB8*AD8*(1+AE8)*MAX(0,N8-AC8),0)),0) -> 0 | AS8: =AQ8+AR8 -> 0 | AT8: =IFERROR(MAX(0,N8-M8),0) -> 0 | AU8: =IFERROR(MAX(0,N8-AI8),0) -> 0 | AV8: =IF(AL8="Да",MIN(AH8,AJ8*AU8),0) -> 0 | AW8: =AV8*AK8 -> #VALUE! | AX8: =AS8*AH8 -> 0 | AY8: =AX8+AW8 -> #VALUE! | AZ8: =IF(AND(A8<>"",B8<>"",C8<>"",D8>0,E8>0,N8<>"",AH8>0,O8="Да",P8="Да",BZ8="ПОЛНО",ABS(AN8-1)<='03_Настройки'!$B$5,IF(T8>0,AND(U8<>"",V8>0),TRUE()),IF(X8>0,AND(Y8<>"",Z8>0),TRUE()),IF(AB8>0,AND(AC8<>"",AD8>0),TRUE()),OR(BM8="",BM8="Активна")),"Да","Нет") -> Нет | BA8: =IF(AM8>=1,"Да","Нет") -> Нет | BB8: =IF(AND(AZ8="Да",BA8="Да",COUNTIFS($A$4:$A$203,A8,$B$4:$B$203,B8,$AZ$4:$AZ$203,"Да",$BA$4:$BA$203,"Да",$AX$4:$AX$203,"<"&AX8)=0,COUNTIFS($A$4:$A$203,A8,$B$4:$B$203,B8,$AZ$4:$AZ$203,"Да",$BA$4:$BA$203,"Да",$AX$4:$AX$203,"="&AX8,$BF$4:$BF$203,"<"&BF8)=0),"ДА","") | BC8: =IF(AND(AZ8="Да",BA8="Да",COUNTIFS($A$4:$A$203,A8,$B$4:$B$203,B8,$AZ$4:$AZ$203,"Да",$BA$4:$BA$203,"Да",$N$4:$N$203,"<"&N8)=0,COUNTIFS($A$4:$A$203,A8,$B$4:$B$203,B8,$AZ$4:$AZ$203,"Да",$BA$4:$BA$203,"Да",$N$4:$N$203,"="&N8,$BF$4:$BF$203,"<"&BF8)=0),"ДА","") | BD8: =IF(AND(AZ8="Да",BA8="Да",COUNTIFS($A$4:$A$203,A8,$B$4:$B$203,B8,$AZ$4:$AZ$203,"Да",$BA$4:$BA$203,"Да",$AY$4:$AY$203,"<"&AY8)=0,COUNTIFS($A$4:$A$203,A8,$B$4:$B$203,B8,$AZ$4:$AZ$203,"Да",$BA$4:$BA$203,"Да",$AY$4:$AY$203,"="&AY8,$BF$4:$BF$203,"<"&BF8)=0),"ДА","") | BE8: =IF(A8="","",IF(BZ8<>"ПОЛНО","BLOCK: неполная форма",IF(O8<>"Да","BLOCK: ввоз не разрешён",IF(P8<>"Да","BLOCK: документы не подтверждены",IF(ABS(AN8-1)>'03_Настройки'!$B$5,"BLOCK: платежи не 100%",IF(AND(BM8<>"",BM8<>"Активна"),"BLOCK: позиция "&BM8,IF(BA8<>"Да","PARTIAL: не покрывает потребность",IF(BB8="ДА","самый дешёвый"&IF(BC8="ДА"," + быстрый","")&IF(BD8="ДА"," + optimal",""),IF(BC8="ДА","самый быстрый"&IF(BD8="ДА"," + optimal",""),IF(BD8="ДА","optimal","Допущен")))))))))) | BF8: =ROW() -> 8 | BN8: =IF(BG8+BH8=0,"",IF(BG8+BH8<>D8,"⚠ SIM+eSIM≠Доступно","OK")) | BO8: =IF($C8="","",IF(TRIM(IF(O8<>"Да","⚠Ввоз ","")&IF(P8<>"Да","⚠Документы ","")&IF(AND(BG8+BH8>0,D8>0,BG8+BH8<>D8),"⚠SIM/eSIM ","")&IF(BZ8<>"ПОЛНО","⚠НеполнаяФорма ",""))="","OK",TRIM(IF(O8<>"Да","⚠Ввоз ","")&IF(P8<>"Да","⚠Документы ","")&IF(AND(BG8+BH8>0,D8>0,BG8+BH8<>D8),"⚠SIM/eSIM ","")&IF(BZ8<>"ПОЛНО","⚠НеполнаяФорма ","")))) | BX8: =IF(OR(BV8<>"",BW8<>""),"Да","") | BZ8: =IF(A8="","",IF(AND(BT8<>"",BJ8<>"",CA8<>"",BK8<>"",OR(BG8<>"",BH8<>""),BM8<>""),"ПОЛНО","НЕПОЛНО"))
H9: =IFERROR(VLOOKUP(C9,'01_Поставщики'!$A$4:$M$11,2,FALSE()),"") | J9: =IFERROR(VLOOKUP(C9,'01_Поставщики'!$A$4:$M$11,8,FALSE()),"") | K9: =IFERROR(VLOOKUP(C9,'01_Поставщики'!$A$4:$M$11,4,FALSE()),"") | L9: =IFERROR(VLOOKUP(C9,'01_Поставщики'!$A$4:$M$11,10,FALSE()),"") | M9: =IF(OR(A9="",B9=""),"",IFERROR(SUMIFS('04_Потребность'!$B$4:$B$103,'04_Потребность'!$A$4:$A$103,A9,'04_Потребность'!$C$4:$C$103,B9),0)) | T9: =IFERROR(INDEX('02_Схемы оплаты'!$C$4:$C$19,MATCH($C9&"|"&$G9,'02_Схемы оплаты'!$H$4:$H$19,0)),0) -> 0 | X9: =IFERROR(INDEX('02_Схемы оплаты'!$D$4:$D$19,MATCH($C9&"|"&$G9,'02_Схемы оплаты'!$H$4:$H$19,0)),0) -> 0 | AB9: =IFERROR(INDEX('02_Схемы оплаты'!$E$4:$E$19,MATCH($C9&"|"&$G9,'02_Схемы оплаты'!$H$4:$H$19,0)),0) -> 0 | AH9: =IFERROR(SUMIFS('04_Потребность'!$D$4:$D$103,'04_Потребность'!$A$4:$A$103,A9,'04_Потребность'!$C$4:$C$103,B9),0) -> 0 | AI9: =IF(OR(A9="",B9=""),"",IFERROR(SUMIFS('04_Потребность'!$E$4:$E$103,'04_Потребность'!$A$4:$A$103,A9,'04_Потребность'!$C$4:$C$103,B9),0)) | AJ9: =IF(OR(A9="",B9=""),"",IFERROR(SUMIFS('04_Потребность'!$F$4:$F$103,'04_Потребность'!$A$4:$A$103,A9,'04_Потребность'!$C$4:$C$103,B9),0)) | AK9: =IF(OR(A9="",B9=""),"",IFERROR(SUMIFS('04_Потребность'!$G$4:$G$103,'04_Потребность'!$A$4:$A$103,A9,'04_Потребность'!$C$4:$C$103,B9),0)) | AL9: =IF('03_Настройки'!$B$7="Нет","Нет",IF(COUNTIFS('04_Потребность'!$A$4:$A$103,A9,'04_Потребность'!$C$4:$C$103,B9,'04_Потребность'!$H$4:$H$103,"Да")>0,"Да","Нет")) -> Нет | AM9: =IFERROR(MIN(1,D9/AH9),0) -> 0 | AN9: =SUM(T9,X9,AB9) -> 0 | AO9: =IFERROR(E9*(T9*V9*(1+W9)+X9*Z9*(1+AA9)+AB9*AD9*(1+AE9)),0) -> 0 | AP9: =AO9*S9 -> 0 | AQ9: =AO9+AP9+Q9+R9 -> 0 | AR9: =IFERROR(E9*'03_Настройки'!$B$4/365*(IF(T9>0,T9*V9*(1+W9)*MAX(0,N9-U9),0)+IF(X9>0,X9*Z9*(1+AA9)*MAX(0,N9-Y9),0)+IF(AB9>0,AB9*AD9*(1+AE9)*MAX(0,N9-AC9),0)),0) -> 0 | AS9: =AQ9+AR9 -> 0 | AT9: =IFERROR(MAX(0,N9-M9),0) -> 0 | AU9: =IFERROR(MAX(0,N9-AI9),0) -> 0 | AV9: =IF(AL9="Да",MIN(AH9,AJ9*AU9),0) -> 0 | AW9: =AV9*AK9 -> #VALUE! | AX9: =AS9*AH9 -> 0 | AY9: =AX9+AW9 -> #VALUE! | AZ9: =IF(AND(A9<>"",B9<>"",C9<>"",D9>0,E9>0,N9<>"",AH9>0,O9="Да",P9="Да",BZ9="ПОЛНО",ABS(AN9-1)<='03_Настройки'!$B$5,IF(T9>0,AND(U9<>"",V9>0),TRUE()),IF(X9>0,AND(Y9<>"",Z9>0),TRUE()),IF(AB9>0,AND(AC9<>"",AD9>0),TRUE()),OR(BM9="",BM9="Активна")),"Да","Нет") -> Нет | BA9: =IF(AM9>=1,"Да","Нет") -> Нет | BB9: =IF(AND(AZ9="Да",BA9="Да",COUNTIFS($A$4:$A$203,A9,$B$4:$B$203,B9,$AZ$4:$AZ$203,"Да",$BA$4:$BA$203,"Да",$AX$4:$AX$203,"<"&AX9)=0,COUNTIFS($A$4:$A$203,A9,$B$4:$B$203,B9,$AZ$4:$AZ$203,"Да",$BA$4:$BA$203,"Да",$AX$4:$AX$203,"="&AX9,$BF$4:$BF$203,"<"&BF9)=0),"ДА","") | BC9: =IF(AND(AZ9="Да",BA9="Да",COUNTIFS($A$4:$A$203,A9,$B$4:$B$203,B9,$AZ$4:$AZ$203,"Да",$BA$4:$BA$203,"Да",$N$4:$N$203,"<"&N9)=0,COUNTIFS($A$4:$A$203,A9,$B$4:$B$203,B9,$AZ$4:$AZ$203,"Да",$BA$4:$BA$203,"Да",$N$4:$N$203,"="&N9,$BF$4:$BF$203,"<"&BF9)=0),"ДА","") | BD9: =IF(AND(AZ9="Да",BA9="Да",COUNTIFS($A$4:$A$203,A9,$B$4:$B$203,B9,$AZ$4:$AZ$203,"Да",$BA$4:$BA$203,"Да",$AY$4:$AY$203,"<"&AY9)=0,COUNTIFS($A$4:$A$203,A9,$B$4:$B$203,B9,$AZ$4:$AZ$203,"Да",$BA$4:$BA$203,"Да",$AY$4:$AY$203,"="&AY9,$BF$4:$BF$203,"<"&BF9)=0),"ДА","") | BE9: =IF(A9="","",IF(BZ9<>"ПОЛНО","BLOCK: неполная форма",IF(O9<>"Да","BLOCK: ввоз не разрешён",IF(P9<>"Да","BLOCK: документы не подтверждены",IF(ABS(AN9-1)>'03_Настройки'!$B$5,"BLOCK: платежи не 100%",IF(AND(BM9<>"",BM9<>"Активна"),"BLOCK: позиция "&BM9,IF(BA9<>"Да","PARTIAL: не покрывает потребность",IF(BB9="ДА","самый дешёвый"&IF(BC9="ДА"," + быстрый","")&IF(BD9="ДА"," + optimal",""),IF(BC9="ДА","самый быстрый"&IF(BD9="ДА"," + optimal",""),IF(BD9="ДА","optimal","Допущен")))))))))) | BF9: =ROW() -> 9 | BN9: =IF(BG9+BH9=0,"",IF(BG9+BH9<>D9,"⚠ SIM+eSIM≠Доступно","OK")) | BO9: =IF($C9="","",IF(TRIM(IF(O9<>"Да","⚠Ввоз ","")&IF(P9<>"Да","⚠Документы ","")&IF(AND(BG9+BH9>0,D9>0,BG9+BH9<>D9),"⚠SIM/eSIM ","")&IF(BZ9<>"ПОЛНО","⚠НеполнаяФорма ",""))="","OK",TRIM(IF(O9<>"Да","⚠Ввоз ","")&IF(P9<>"Да","⚠Документы ","")&IF(AND(BG9+BH9>0,D9>0,BG9+BH9<>D9),"⚠SIM/eSIM ","")&IF(BZ9<>"ПОЛНО","⚠НеполнаяФорма ","")))) | BX9: =IF(OR(BV9<>"",BW9<>""),"Да","") | BZ9: =IF(A9="","",IF(AND(BT9<>"",BJ9<>"",CA9<>"",BK9<>"",OR(BG9<>"",BH9<>""),BM9<>""),"ПОЛНО","НЕПОЛНО"))
H10: =IFERROR(VLOOKUP(C10,'01_Поставщики'!$A$4:$M$11,2,FALSE()),"") | J10: =IFERROR(VLOOKUP(C10,'01_Поставщики'!$A$4:$M$11,8,FALSE()),"") | K10: =IFERROR(VLOOKUP(C10,'01_Поставщики'!$A$4:$M$11,4,FALSE()),"") | L10: =IFERROR(VLOOKUP(C10,'01_Поставщики'!$A$4:$M$11,10,FALSE()),"") | M10: =IF(OR(A10="",B10=""),"",IFERROR(SUMIFS('04_Потребность'!$B$4:$B$103,'04_Потребность'!$A$4:$A$103,A10,'04_Потребность'!$C$4:$C$103,B10),0)) | T10: =IFERROR(INDEX('02_Схемы оплаты'!$C$4:$C$19,MATCH($C10&"|"&$G10,'02_Схемы оплаты'!$H$4:$H$19,0)),0) -> 0 | X10: =IFERROR(INDEX('02_Схемы оплаты'!$D$4:$D$19,MATCH($C10&"|"&$G10,'02_Схемы оплаты'!$H$4:$H$19,0)),0) -> 0 | AB10: =IFERROR(INDEX('02_Схемы оплаты'!$E$4:$E$19,MATCH($C10&"|"&$G10,'02_Схемы оплаты'!$H$4:$H$19,0)),0) -> 0 | AH10: =IFERROR(SUMIFS('04_Потребность'!$D$4:$D$103,'04_Потребность'!$A$4:$A$103,A10,'04_Потребность'!$C$4:$C$103,B10),0) -> 0 | AI10: =IF(OR(A10="",B10=""),"",IFERROR(SUMIFS('04_Потребность'!$E$4:$E$103,'04_Потребность'!$A$4:$A$103,A10,'04_Потребность'!$C$4:$C$103,B10),0)) | AJ10: =IF(OR(A10="",B10=""),"",IFERROR(SUMIFS('04_Потребность'!$F$4:$F$103,'04_Потребность'!$A$4:$A$103,A10,'04_Потребность'!$C$4:$C$103,B10),0)) | AK10: =IF(OR(A10="",B10=""),"",IFERROR(SUMIFS('04_Потребность'!$G$4:$G$103,'04_Потребность'!$A$4:$A$103,A10,'04_Потребность'!$C$4:$C$103,B10),0)) | AL10: =IF('03_Настройки'!$B$7="Нет","Нет",IF(COUNTIFS('04_Потребность'!$A$4:$A$103,A10,'04_Потребность'!$C$4:$C$103,B10,'04_Потребность'!$H$4:$H$103,"Да")>0,"Да","Нет")) -> Нет | AM10: =IFERROR(MIN(1,D10/AH10),0) -> 0 | AN10: =SUM(T10,X10,AB10) -> 0 | AO10: =IFERROR(E10*(T10*V10*(1+W10)+X10*Z10*(1+AA10)+AB10*AD10*(1+AE10)),0) -> 0 | AP10: =AO10*S10 -> 0 | AQ10: =AO10+AP10+Q10+R10 -> 0 | AR10: =IFERROR(E10*'03_Настройки'!$B$4/365*(IF(T10>0,T10*V10*(1+W10)*MAX(0,N10-U10),0)+IF(X10>0,X10*Z10*(1+AA10)*MAX(0,N10-Y10),0)+IF(AB10>0,AB10*AD10*(1+AE10)*MAX(0,N10-AC10),0)),0) -> 0 | AS10: =AQ10+AR10 -> 0 | AT10: =IFERROR(MAX(0,N10-M10),0) -> 0 | AU10: =IFERROR(MAX(0,N10-AI10),0) -> 0 | AV10: =IF(AL10="Да",MIN(AH10,AJ10*AU10),0) -> 0 | AW10: =AV10*AK10 -> #VALUE! | AX10: =AS10*AH10 -> 0 | AY10: =AX10+AW10 -> #VALUE! | AZ10: =IF(AND(A10<>"",B10<>"",C10<>"",D10>0,E10>0,N10<>"",AH10>0,O10="Да",P10="Да",BZ10="ПОЛНО",ABS(AN10-1)<='03_Настройки'!$B$5,IF(T10>0,AND(U10<>"",V10>0),TRUE()),IF(X10>0,AND(Y10<>"",Z10>0),TRUE()),IF(AB10>0,AND(AC10<>"",AD10>0),TRUE()),OR(BM10="",BM10="Активна")),"Да","Нет") -> Нет | BA10: =IF(AM10>=1,"Да","Нет") -> Нет | BB10: =IF(AND(AZ10="Да",BA10="Да",COUNTIFS($A$4:$A$203,A10,$B$4:$B$203,B10,$AZ$4:$AZ$203,"Да",$BA$4:$BA$203,"Да",$AX$4:$AX$203,"<"&AX10)=0,COUNTIFS($A$4:$A$203,A10,$B$4:$B$203,B10,$AZ$4:$AZ$203,"Да",$BA$4:$BA$203,"Да",$AX$4:$AX$203,"="&AX10,$BF$4:$BF$203,"<"&BF10)=0),"ДА","") | BC10: =IF(AND(AZ10="Да",BA10="Да",COUNTIFS($A$4:$A$203,A10,$B$4:$B$203,B10,$AZ$4:$AZ$203,"Да",$BA$4:$BA$203,"Да",$N$4:$N$203,"<"&N10)=0,COUNTIFS($A$4:$A$203,A10,$B$4:$B$203,B10,$AZ$4:$AZ$203,"Да",$BA$4:$BA$203,"Да",$N$4:$N$203,"="&N10,$BF$4:$BF$203,"<"&BF10)=0),"ДА","") | BD10: =IF(AND(AZ10="Да",BA10="Да",COUNTIFS($A$4:$A$203,A10,$B$4:$B$203,B10,$AZ$4:$AZ$203,"Да",$BA$4:$BA$203,"Да",$AY$4:$AY$203,"<"&AY10)=0,COUNTIFS($A$4:$A$203,A10,$B$4:$B$203,B10,$AZ$4:$AZ$203,"Да",$BA$4:$BA$203,"Да",$AY$4:$AY$203,"="&AY10,$BF$4:$BF$203,"<"&BF10)=0),"ДА","") | BE10: =IF(A10="","",IF(BZ10<>"ПОЛНО","BLOCK: неполная форма",IF(O10<>"Да","BLOCK: ввоз не разрешён",IF(P10<>"Да","BLOCK: документы не подтверждены",IF(ABS(AN10-1)>'03_Настройки'!$B$5,"BLOCK: платежи не 100%",IF(AND(BM10<>"",BM10<>"Активна"),"BLOCK: позиция "&BM10,IF(BA10<>"Да","PARTIAL: не покрывает потребность",IF(BB10="ДА","самый дешёвый"&IF(BC10="ДА"," + быстрый","")&IF(BD10="ДА"," + optimal",""),IF(BC10="ДА","самый быстрый"&IF(BD10="ДА"," + optimal",""),IF(BD10="ДА","optimal","Допущен")))))))))) | BF10: =ROW() -> 10 | BN10: =IF(BG10+BH10=0,"",IF(BG10+BH10<>D10,"⚠ SIM+eSIM≠Доступно","OK")) | BO10: =IF($C10="","",IF(TRIM(IF(O10<>"Да","⚠Ввоз ","")&IF(P10<>"Да","⚠Документы ","")&IF(AND(BG10+BH10>0,D10>0,BG10+BH10<>D10),"⚠SIM/eSIM ","")&IF(BZ10<>"ПОЛНО","⚠НеполнаяФорма ",""))="","OK",TRIM(IF(O10<>"Да","⚠Ввоз ","")&IF(P10<>"Да","⚠Документы ","")&IF(AND(BG10+BH10>0,D10>0,BG10+BH10<>D10),"⚠SIM/eSIM ","")&IF(BZ10<>"ПОЛНО","⚠НеполнаяФорма ","")))) | BX10: =IF(OR(BV10<>"",BW10<>""),"Да","") | BZ10: =IF(A10="","",IF(AND(BT10<>"",BJ10<>"",CA10<>"",BK10<>"",OR(BG10<>"",BH10<>""),BM10<>""),"ПОЛНО","НЕПОЛНО"))
H11: =IFERROR(VLOOKUP(C11,'01_Поставщики'!$A$4:$M$11,2,FALSE()),"") | J11: =IFERROR(VLOOKUP(C11,'01_Поставщики'!$A$4:$M$11,8,FALSE()),"") | K11: =IFERROR(VLOOKUP(C11,'01_Поставщики'!$A$4:$M$11,4,FALSE()),"") | L11: =IFERROR(VLOOKUP(C11,'01_Поставщики'!$A$4:$M$11,10,FALSE()),"") | M11: =IF(OR(A11="",B11=""),"",IFERROR(SUMIFS('04_Потребность'!$B$4:$B$103,'04_Потребность'!$A$4:$A$103,A11,'04_Потребность'!$C$4:$C$103,B11),0)) | T11: =IFERROR(INDEX('02_Схемы оплаты'!$C$4:$C$19,MATCH($C11&"|"&$G11,'02_Схемы оплаты'!$H$4:$H$19,0)),0) -> 0 | X11: =IFERROR(INDEX('02_Схемы оплаты'!$D$4:$D$19,MATCH($C11&"|"&$G11,'02_Схемы оплаты'!$H$4:$H$19,0)),0) -> 0 | AB11: =IFERROR(INDEX('02_Схемы оплаты'!$E$4:$E$19,MATCH($C11&"|"&$G11,'02_Схемы оплаты'!$H$4:$H$19,0)),0) -> 0 | AH11: =IFERROR(SUMIFS('04_Потребность'!$D$4:$D$103,'04_Потребность'!$A$4:$A$103,A11,'04_Потребность'!$C$4:$C$103,B11),0) -> 0 | AI11: =IF(OR(A11="",B11=""),"",IFERROR(SUMIFS('04_Потребность'!$E$4:$E$103,'04_Потребность'!$A$4:$A$103,A11,'04_Потребность'!$C$4:$C$103,B11),0)) | AJ11: =IF(OR(A11="",B11=""),"",IFERROR(SUMIFS('04_Потребность'!$F$4:$F$103,'04_Потребность'!$A$4:$A$103,A11,'04_Потребность'!$C$4:$C$103,B11),0)) | AK11: =IF(OR(A11="",B11=""),"",IFERROR(SUMIFS('04_Потребность'!$G$4:$G$103,'04_Потребность'!$A$4:$A$103,A11,'04_Потребность'!$C$4:$C$103,B11),0)) | AL11: =IF('03_Настройки'!$B$7="Нет","Нет",IF(COUNTIFS('04_Потребность'!$A$4:$A$103,A11,'04_Потребность'!$C$4:$C$103,B11,'04_Потребность'!$H$4:$H$103,"Да")>0,"Да","Нет")) -> Нет | AM11: =IFERROR(MIN(1,D11/AH11),0) -> 0 | AN11: =SUM(T11,X11,AB11) -> 0 | AO11: =IFERROR(E11*(T11*V11*(1+W11)+X11*Z11*(1+AA11)+AB11*AD11*(1+AE11)),0) -> 0 | AP11: =AO11*S11 -> 0 | AQ11: =AO11+AP11+Q11+R11 -> 0 | AR11: =IFERROR(E11*'03_Настройки'!$B$4/365*(IF(T11>0,T11*V11*(1+W11)*MAX(0,N11-U11),0)+IF(X11>0,X11*Z11*(1+AA11)*MAX(0,N11-Y11),0)+IF(AB11>0,AB11*AD11*(1+AE11)*MAX(0,N11-AC11),0)),0) -> 0 | AS11: =AQ11+AR11 -> 0 | AT11: =IFERROR(MAX(0,N11-M11),0) -> 0 | AU11: =IFERROR(MAX(0,N11-AI11),0) -> 0 | AV11: =IF(AL11="Да",MIN(AH11,AJ11*AU11),0) -> 0 | AW11: =AV11*AK11 -> #VALUE! | AX11: =AS11*AH11 -> 0 | AY11: =AX11+AW11 -> #VALUE! | AZ11: =IF(AND(A11<>"",B11<>"",C11<>"",D11>0,E11>0,N11<>"",AH11>0,O11="Да",P11="Да",BZ11="ПОЛНО",ABS(AN11-1)<='03_Настройки'!$B$5,IF(T11>0,AND(U11<>"",V11>0),TRUE()),IF(X11>0,AND(Y11<>"",Z11>0),TRUE()),IF(AB11>0,AND(AC11<>"",AD11>0),TRUE()),OR(BM11="",BM11="Активна")),"Да","Нет") -> Нет | BA11: =IF(AM11>=1,"Да","Нет") -> Нет | BB11: =IF(AND(AZ11="Да",BA11="Да",COUNTIFS($A$4:$A$203,A11,$B$4:$B$203,B11,$AZ$4:$AZ$203,"Да",$BA$4:$BA$203,"Да",$AX$4:$AX$203,"<"&AX11)=0,COUNTIFS($A$4:$A$203,A11,$B$4:$B$203,B11,$AZ$4:$AZ$203,"Да",$BA$4:$BA$203,"Да",$AX$4:$AX$203,"="&AX11,$BF$4:$BF$203,"<"&BF11)=0),"ДА","") | BC11: =IF(AND(AZ11="Да",BA11="Да",COUNTIFS($A$4:$A$203,A11,$B$4:$B$203,B11,$AZ$4:$AZ$203,"Да",$BA$4:$BA$203,"Да",$N$4:$N$203,"<"&N11)=0,COUNTIFS($A$4:$A$203,A11,$B$4:$B$203,B11,$AZ$4:$AZ$203,"Да",$BA$4:$BA$203,"Да",$N$4:$N$203,"="&N11,$BF$4:$BF$203,"<"&BF11)=0),"ДА","") | BD11: =IF(AND(AZ11="Да",BA11="Да",COUNTIFS($A$4:$A$203,A11,$B$4:$B$203,B11,$AZ$4:$AZ$203,"Да",$BA$4:$BA$203,"Да",$AY$4:$AY$203,"<"&AY11)=0,COUNTIFS($A$4:$A$203,A11,$B$4:$B$203,B11,$AZ$4:$AZ$203,"Да",$BA$4:$BA$203,"Да",$AY$4:$AY$203,"="&AY11,$BF$4:$BF$203,"<"&BF11)=0),"ДА","") | BE11: =IF(A11="","",IF(BZ11<>"ПОЛНО","BLOCK: неполная форма",IF(O11<>"Да","BLOCK: ввоз не разрешён",IF(P11<>"Да","BLOCK: документы не подтверждены",IF(ABS(AN11-1)>'03_Настройки'!$B$5,"BLOCK: платежи не 100%",IF(AND(BM11<>"",BM11<>"Активна"),"BLOCK: позиция "&BM11,IF(BA11<>"Да","PARTIAL: не покрывает потребность",IF(BB11="ДА","самый дешёвый"&IF(BC11="ДА"," + быстрый","")&IF(BD11="ДА"," + optimal",""),IF(BC11="ДА","самый быстрый"&IF(BD11="ДА"," + optimal",""),IF(BD11="ДА","optimal","Допущен")))))))))) | BF11: =ROW() -> 11 | BN11: =IF(BG11+BH11=0,"",IF(BG11+BH11<>D11,"⚠ SIM+eSIM≠Доступно","OK")) | BO11: =IF($C11="","",IF(TRIM(IF(O11<>"Да","⚠Ввоз ","")&IF(P11<>"Да","⚠Документы ","")&IF(AND(BG11+BH11>0,D11>0,BG11+BH11<>D11),"⚠SIM/eSIM ","")&IF(BZ11<>"ПОЛНО","⚠НеполнаяФорма ",""))="","OK",TRIM(IF(O11<>"Да","⚠Ввоз ","")&IF(P11<>"Да","⚠Документы ","")&IF(AND(BG11+BH11>0,D11>0,BG11+BH11<>D11),"⚠SIM/eSIM ","")&IF(BZ11<>"ПОЛНО","⚠НеполнаяФорма ","")))) | BX11: =IF(OR(BV11<>"",BW11<>""),"Да","") | BZ11: =IF(A11="","",IF(AND(BT11<>"",BJ11<>"",CA11<>"",BK11<>"",OR(BG11<>"",BH11<>""),BM11<>""),"ПОЛНО","НЕПОЛНО"))
H12: =IFERROR(VLOOKUP(C12,'01_Поставщики'!$A$4:$M$11,2,FALSE()),"") | J12: =IFERROR(VLOOKUP(C12,'01_Поставщики'!$A$4:$M$11,8,FALSE()),"") | K12: =IFERROR(VLOOKUP(C12,'01_Поставщики'!$A$4:$M$11,4,FALSE()),"") | L12: =IFERROR(VLOOKUP(C12,'01_Поставщики'!$A$4:$M$11,10,FALSE()),"") | M12: =IF(OR(A12="",B12=""),"",IFERROR(SUMIFS('04_Потребность'!$B$4:$B$103,'04_Потребность'!$A$4:$A$103,A12,'04_Потребность'!$C$4:$C$103,B12),0)) | T12: =IFERROR(INDEX('02_Схемы оплаты'!$C$4:$C$19,MATCH($C12&"|"&$G12,'02_Схемы оплаты'!$H$4:$H$19,0)),0) -> 0 | X12: =IFERROR(INDEX('02_Схемы оплаты'!$D$4:$D$19,MATCH($C12&"|"&$G12,'02_Схемы оплаты'!$H$4:$H$19,0)),0) -> 0 | AB12: =IFERROR(INDEX('02_Схемы оплаты'!$E$4:$E$19,MATCH($C12&"|"&$G12,'02_Схемы оплаты'!$H$4:$H$19,0)),0) -> 0 | AH12: =IFERROR(SUMIFS('04_Потребность'!$D$4:$D$103,'04_Потребность'!$A$4:$A$103,A12,'04_Потребность'!$C$4:$C$103,B12),0) -> 0 | AI12: =IF(OR(A12="",B12=""),"",IFERROR(SUMIFS('04_Потребность'!$E$4:$E$103,'04_Потребность'!$A$4:$A$103,A12,'04_Потребность'!$C$4:$C$103,B12),0)) | AJ12: =IF(OR(A12="",B12=""),"",IFERROR(SUMIFS('04_Потребность'!$F$4:$F$103,'04_Потребность'!$A$4:$A$103,A12,'04_Потребность'!$C$4:$C$103,B12),0)) | AK12: =IF(OR(A12="",B12=""),"",IFERROR(SUMIFS('04_Потребность'!$G$4:$G$103,'04_Потребность'!$A$4:$A$103,A12,'04_Потребность'!$C$4:$C$103,B12),0)) | AL12: =IF('03_Настройки'!$B$7="Нет","Нет",IF(COUNTIFS('04_Потребность'!$A$4:$A$103,A12,'04_Потребность'!$C$4:$C$103,B12,'04_Потребность'!$H$4:$H$103,"Да")>0,"Да","Нет")) -> Нет | AM12: =IFERROR(MIN(1,D12/AH12),0) -> 0 | AN12: =SUM(T12,X12,AB12) -> 0 | AO12: =IFERROR(E12*(T12*V12*(1+W12)+X12*Z12*(1+AA12)+AB12*AD12*(1+AE12)),0) -> 0 | AP12: =AO12*S12 -> 0 | AQ12: =AO12+AP12+Q12+R12 -> 0 | AR12: =IFERROR(E12*'03_Настройки'!$B$4/365*(IF(T12>0,T12*V12*(1+W12)*MAX(0,N12-U12),0)+IF(X12>0,X12*Z12*(1+AA12)*MAX(0,N12-Y12),0)+IF(AB12>0,AB12*AD12*(1+AE12)*MAX(0,N12-AC12),0)),0) -> 0 | AS12: =AQ12+AR12 -> 0 | AT12: =IFERROR(MAX(0,N12-M12),0) -> 0 | AU12: =IFERROR(MAX(0,N12-AI12),0) -> 0 | AV12: =IF(AL12="Да",MIN(AH12,AJ12*AU12),0) -> 0 | AW12: =AV12*AK12 -> #VALUE! | AX12: =AS12*AH12 -> 0 | AY12: =AX12+AW12 -> #VALUE! | AZ12: =IF(AND(A12<>"",B12<>"",C12<>"",D12>0,E12>0,N12<>"",AH12>0,O12="Да",P12="Да",BZ12="ПОЛНО",ABS(AN12-1)<='03_Настройки'!$B$5,IF(T12>0,AND(U12<>"",V12>0),TRUE()),IF(X12>0,AND(Y12<>"",Z12>0),TRUE()),IF(AB12>0,AND(AC12<>"",AD12>0),TRUE()),OR(BM12="",BM12="Активна")),"Да","Нет") -> Нет | BA12: =IF(AM12>=1,"Да","Нет") -> Нет | BB12: =IF(AND(AZ12="Да",BA12="Да",COUNTIFS($A$4:$A$203,A12,$B$4:$B$203,B12,$AZ$4:$AZ$203,"Да",$BA$4:$BA$203,"Да",$AX$4:$AX$203,"<"&AX12)=0,COUNTIFS($A$4:$A$203,A12,$B$4:$B$203,B12,$AZ$4:$AZ$203,"Да",$BA$4:$BA$203,"Да",$AX$4:$AX$203,"="&AX12,$BF$4:$BF$203,"<"&BF12)=0),"ДА","") | BC12: =IF(AND(AZ12="Да",BA12="Да",COUNTIFS($A$4:$A$203,A12,$B$4:$B$203,B12,$AZ$4:$AZ$203,"Да",$BA$4:$BA$203,"Да",$N$4:$N$203,"<"&N12)=0,COUNTIFS($A$4:$A$203,A12,$B$4:$B$203,B12,$AZ$4:$AZ$203,"Да",$BA$4:$BA$203,"Да",$N$4:$N$203,"="&N12,$BF$4:$BF$203,"<"&BF12)=0),"ДА","") | BD12: =IF(AND(AZ12="Да",BA12="Да",COUNTIFS($A$4:$A$203,A12,$B$4:$B$203,B12,$AZ$4:$AZ$203,"Да",$BA$4:$BA$203,"Да",$AY$4:$AY$203,"<"&AY12)=0,COUNTIFS($A$4:$A$203,A12,$B$4:$B$203,B12,$AZ$4:$AZ$203,"Да",$BA$4:$BA$203,"Да",$AY$4:$AY$203,"="&AY12,$BF$4:$BF$203,"<"&BF12)=0),"ДА","") | BE12: =IF(A12="","",IF(BZ12<>"ПОЛНО","BLOCK: неполная форма",IF(O12<>"Да","BLOCK: ввоз не разрешён",IF(P12<>"Да","BLOCK: документы не подтверждены",IF(ABS(AN12-1)>'03_Настройки'!$B$5,"BLOCK: платежи не 100%",IF(AND(BM12<>"",BM12<>"Активна"),"BLOCK: позиция "&BM12,IF(BA12<>"Да","PARTIAL: не покрывает потребность",IF(BB12="ДА","самый дешёвый"&IF(BC12="ДА"," + быстрый","")&IF(BD12="ДА"," + optimal",""),IF(BC12="ДА","самый быстрый"&IF(BD12="ДА"," + optimal",""),IF(BD12="ДА","optimal","Допущен")))))))))) | BF12: =ROW() -> 12 | BN12: =IF(BG12+BH12=0,"",IF(BG12+BH12<>D12,"⚠ SIM+eSIM≠Доступно","OK")) | BO12: =IF($C12="","",IF(TRIM(IF(O12<>"Да","⚠Ввоз ","")&IF(P12<>"Да","⚠Документы ","")&IF(AND(BG12+BH12>0,D12>0,BG12+BH12<>D12),"⚠SIM/eSIM ","")&IF(BZ12<>"ПОЛНО","⚠НеполнаяФорма ",""))="","OK",TRIM(IF(O12<>"Да","⚠Ввоз ","")&IF(P12<>"Да","⚠Документы ","")&IF(AND(BG12+BH12>0,D12>0,BG12+BH12<>D12),"⚠SIM/eSIM ","")&IF(BZ12<>"ПОЛНО","⚠НеполнаяФорма ","")))) | BX12: =IF(OR(BV12<>"",BW12<>""),"Да","") | BZ12: =IF(A12="","",IF(AND(BT12<>"",BJ12<>"",CA12<>"",BK12<>"",OR(BG12<>"",BH12<>""),BM12<>""),"ПОЛНО","НЕПОЛНО"))
H13: =IFERROR(VLOOKUP(C13,'01_Поставщики'!$A$4:$M$11,2,FALSE()),"") | J13: =IFERROR(VLOOKUP(C13,'01_Поставщики'!$A$4:$M$11,8,FALSE()),"") | K13: =IFERROR(VLOOKUP(C13,'01_Поставщики'!$A$4:$M$11,4,FALSE()),"") | L13: =IFERROR(VLOOKUP(C13,'01_Поставщики'!$A$4:$M$11,10,FALSE()),"") | M13: =IF(OR(A13="",B13=""),"",IFERROR(SUMIFS('04_Потребность'!$B$4:$B$103,'04_Потребность'!$A$4:$A$103,A13,'04_Потребность'!$C$4:$C$103,B13),0)) | T13: =IFERROR(INDEX('02_Схемы оплаты'!$C$4:$C$19,MATCH($C13&"|"&$G13,'02_Схемы оплаты'!$H$4:$H$19,0)),0) -> 0 | X13: =IFERROR(INDEX('02_Схемы оплаты'!$D$4:$D$19,MATCH($C13&"|"&$G13,'02_Схемы оплаты'!$H$4:$H$19,0)),0) -> 0 | AB13: =IFERROR(INDEX('02_Схемы оплаты'!$E$4:$E$19,MATCH($C13&"|"&$G13,'02_Схемы оплаты'!$H$4:$H$19,0)),0) -> 0 | AH13: =IFERROR(SUMIFS('04_Потребность'!$D$4:$D$103,'04_Потребность'!$A$4:$A$103,A13,'04_Потребность'!$C$4:$C$103,B13),0) -> 0 | AI13: =IF(OR(A13="",B13=""),"",IFERROR(SUMIFS('04_Потребность'!$E$4:$E$103,'04_Потребность'!$A$4:$A$103,A13,'04_Потребность'!$C$4:$C$103,B13),0)) | AJ13: =IF(OR(A13="",B13=""),"",IFERROR(SUMIFS('04_Потребность'!$F$4:$F$103,'04_Потребность'!$A$4:$A$103,A13,'04_Потребность'!$C$4:$C$103,B13),0)) | AK13: =IF(OR(A13="",B13=""),"",IFERROR(SUMIFS('04_Потребность'!$G$4:$G$103,'04_Потребность'!$A$4:$A$103,A13,'04_Потребность'!$C$4:$C$103,B13),0)) | AL13: =IF('03_Настройки'!$B$7="Нет","Нет",IF(COUNTIFS('04_Потребность'!$A$4:$A$103,A13,'04_Потребность'!$C$4:$C$103,B13,'04_Потребность'!$H$4:$H$103,"Да")>0,"Да","Нет")) -> Нет | AM13: =IFERROR(MIN(1,D13/AH13),0) -> 0 | AN13: =SUM(T13,X13,AB13) -> 0 | AO13: =IFERROR(E13*(T13*V13*(1+W13)+X13*Z13*(1+AA13)+AB13*AD13*(1+AE13)),0) -> 0 | AP13: =AO13*S13 -> 0 | AQ13: =AO13+AP13+Q13+R13 -> 0 | AR13: =IFERROR(E13*'03_Настройки'!$B$4/365*(IF(T13>0,T13*V13*(1+W13)*MAX(0,N13-U13),0)+IF(X13>0,X13*Z13*(1+AA13)*MAX(0,N13-Y13),0)+IF(AB13>0,AB13*AD13*(1+AE13)*MAX(0,N13-AC13),0)),0) -> 0 | AS13: =AQ13+AR13 -> 0 | AT13: =IFERROR(MAX(0,N13-M13),0) -> 0 | AU13: =IFERROR(MAX(0,N13-AI13),0) -> 0 | AV13: =IF(AL13="Да",MIN(AH13,AJ13*AU13),0) -> 0 | AW13: =AV13*AK13 -> #VALUE! | AX13: =AS13*AH13 -> 0 | AY13: =AX13+AW13 -> #VALUE! | AZ13: =IF(AND(A13<>"",B13<>"",C13<>"",D13>0,E13>0,N13<>"",AH13>0,O13="Да",P13="Да",BZ13="ПОЛНО",ABS(AN13-1)<='03_Настройки'!$B$5,IF(T13>0,AND(U13<>"",V13>0),TRUE()),IF(X13>0,AND(Y13<>"",Z13>0),TRUE()),IF(AB13>0,AND(AC13<>"",AD13>0),TRUE()),OR(BM13="",BM13="Активна")),"Да","Нет") -> Нет | BA13: =IF(AM13>=1,"Да","Нет") -> Нет | BB13: =IF(AND(AZ13="Да",BA13="Да",COUNTIFS($A$4:$A$203,A13,$B$4:$B$203,B13,$AZ$4:$AZ$203,"Да",$BA$4:$BA$203,"Да",$AX$4:$AX$203,"<"&AX13)=0,COUNTIFS($A$4:$A$203,A13,$B$4:$B$203,B13,$AZ$4:$AZ$203,"Да",$BA$4:$BA$203,"Да",$AX$4:$AX$203,"="&AX13,$BF$4:$BF$203,"<"&BF13)=0),"ДА","") | BC13: =IF(AND(AZ13="Да",BA13="Да",COUNTIFS($A$4:$A$203,A13,$B$4:$B$203,B13,$AZ$4:$AZ$203,"Да",$BA$4:$BA$203,"Да",$N$4:$N$203,"<"&N13)=0,COUNTIFS($A$4:$A$203,A13,$B$4:$B$203,B13,$AZ$4:$AZ$203,"Да",$BA$4:$BA$203,"Да",$N$4:$N$203,"="&N13,$BF$4:$BF$203,"<"&BF13)=0),"ДА","") | BD13: =IF(AND(AZ13="Да",BA13="Да",COUNTIFS($A$4:$A$203,A13,$B$4:$B$203,B13,$AZ$4:$AZ$203,"Да",$BA$4:$BA$203,"Да",$AY$4:$AY$203,"<"&AY13)=0,COUNTIFS($A$4:$A$203,A13,$B$4:$B$203,B13,$AZ$4:$AZ$203,"Да",$BA$4:$BA$203,"Да",$AY$4:$AY$203,"="&AY13,$BF$4:$BF$203,"<"&BF13)=0),"ДА","") | BE13: =IF(A13="","",IF(BZ13<>"ПОЛНО","BLOCK: неполная форма",IF(O13<>"Да","BLOCK: ввоз не разрешён",IF(P13<>"Да","BLOCK: документы не подтверждены",IF(ABS(AN13-1)>'03_Настройки'!$B$5,"BLOCK: платежи не 100%",IF(AND(BM13<>"",BM13<>"Активна"),"BLOCK: позиция "&BM13,IF(BA13<>"Да","PARTIAL: не покрывает потребность",IF(BB13="ДА","самый дешёвый"&IF(BC13="ДА"," + быстрый","")&IF(BD13="ДА"," + optimal",""),IF(BC13="ДА","самый быстрый"&IF(BD13="ДА"," + optimal",""),IF(BD13="ДА","optimal","Допущен")))))))))) | BF13: =ROW() -> 13 | BN13: =IF(BG13+BH13=0,"",IF(BG13+BH13<>D13,"⚠ SIM+eSIM≠Доступно","OK")) | BO13: =IF($C13="","",IF(TRIM(IF(O13<>"Да","⚠Ввоз ","")&IF(P13<>"Да","⚠Документы ","")&IF(AND(BG13+BH13>0,D13>0,BG13+BH13<>D13),"⚠SIM/eSIM ","")&IF(BZ13<>"ПОЛНО","⚠НеполнаяФорма ",""))="","OK",TRIM(IF(O13<>"Да","⚠Ввоз ","")&IF(P13<>"Да","⚠Документы ","")&IF(AND(BG13+BH13>0,D13>0,BG13+BH13<>D13),"⚠SIM/eSIM ","")&IF(BZ13<>"ПОЛНО","⚠НеполнаяФорма ","")))) | BX13: =IF(OR(BV13<>"",BW13<>""),"Да","") | BZ13: =IF(A13="","",IF(AND(BT13<>"",BJ13<>"",CA13<>"",BK13<>"",OR(BG13<>"",BH13<>""),BM13<>""),"ПОЛНО","НЕПОЛНО"))
H14: =IFERROR(VLOOKUP(C14,'01_Поставщики'!$A$4:$M$11,2,FALSE()),"") | J14: =IFERROR(VLOOKUP(C14,'01_Поставщики'!$A$4:$M$11,8,FALSE()),"") | K14: =IFERROR(VLOOKUP(C14,'01_Поставщики'!$A$4:$M$11,4,FALSE()),"") | L14: =IFERROR(VLOOKUP(C14,'01_Поставщики'!$A$4:$M$11,10,FALSE()),"") | M14: =IF(OR(A14="",B14=""),"",IFERROR(SUMIFS('04_Потребность'!$B$4:$B$103,'04_Потребность'!$A$4:$A$103,A14,'04_Потребность'!$C$4:$C$103,B14),0)) | T14: =IFERROR(INDEX('02_Схемы оплаты'!$C$4:$C$19,MATCH($C14&"|"&$G14,'02_Схемы оплаты'!$H$4:$H$19,0)),0) -> 0 | X14: =IFERROR(INDEX('02_Схемы оплаты'!$D$4:$D$19,MATCH($C14&"|"&$G14,'02_Схемы оплаты'!$H$4:$H$19,0)),0) -> 0 | AB14: =IFERROR(INDEX('02_Схемы оплаты'!$E$4:$E$19,MATCH($C14&"|"&$G14,'02_Схемы оплаты'!$H$4:$H$19,0)),0) -> 0 | AH14: =IFERROR(SUMIFS('04_Потребность'!$D$4:$D$103,'04_Потребность'!$A$4:$A$103,A14,'04_Потребность'!$C$4:$C$103,B14),0) -> 0 | AI14: =IF(OR(A14="",B14=""),"",IFERROR(SUMIFS('04_Потребность'!$E$4:$E$103,'04_Потребность'!$A$4:$A$103,A14,'04_Потребность'!$C$4:$C$103,B14),0)) | AJ14: =IF(OR(A14="",B14=""),"",IFERROR(SUMIFS('04_Потребность'!$F$4:$F$103,'04_Потребность'!$A$4:$A$103,A14,'04_Потребность'!$C$4:$C$103,B14),0)) | AK14: =IF(OR(A14="",B14=""),"",IFERROR(SUMIFS('04_Потребность'!$G$4:$G$103,'04_Потребность'!$A$4:$A$103,A14,'04_Потребность'!$C$4:$C$103,B14),0)) | AL14: =IF('03_Настройки'!$B$7="Нет","Нет",IF(COUNTIFS('04_Потребность'!$A$4:$A$103,A14,'04_Потребность'!$C$4:$C$103,B14,'04_Потребность'!$H$4:$H$103,"Да")>0,"Да","Нет")) -> Нет | AM14: =IFERROR(MIN(1,D14/AH14),0) -> 0 | AN14: =SUM(T14,X14,AB14) -> 0 | AO14: =IFERROR(E14*(T14*V14*(1+W14)+X14*Z14*(1+AA14)+AB14*AD14*(1+AE14)),0) -> 0 | AP14: =AO14*S14 -> 0 | AQ14: =AO14+AP14+Q14+R14 -> 0 | AR14: =IFERROR(E14*'03_Настройки'!$B$4/365*(IF(T14>0,T14*V14*(1+W14)*MAX(0,N14-U14),0)+IF(X14>0,X14*Z14*(1+AA14)*MAX(0,N14-Y14),0)+IF(AB14>0,AB14*AD14*(1+AE14)*MAX(0,N14-AC14),0)),0) -> 0 | AS14: =AQ14+AR14 -> 0 | AT14: =IFERROR(MAX(0,N14-M14),0) -> 0 | AU14: =IFERROR(MAX(0,N14-AI14),0) -> 0 | AV14: =IF(AL14="Да",MIN(AH14,AJ14*AU14),0) -> 0 | AW14: =AV14*AK14 -> #VALUE! | AX14: =AS14*AH14 -> 0 | AY14: =AX14+AW14 -> #VALUE! | AZ14: =IF(AND(A14<>"",B14<>"",C14<>"",D14>0,E14>0,N14<>"",AH14>0,O14="Да",P14="Да",BZ14="ПОЛНО",ABS(AN14-1)<='03_Настройки'!$B$5,IF(T14>0,AND(U14<>"",V14>0),TRUE()),IF(X14>0,AND(Y14<>"",Z14>0),TRUE()),IF(AB14>0,AND(AC14<>"",AD14>0),TRUE()),OR(BM14="",BM14="Активна")),"Да","Нет") -> Нет | BA14: =IF(AM14>=1,"Да","Нет") -> Нет | BB14: =IF(AND(AZ14="Да",BA14="Да",COUNTIFS($A$4:$A$203,A14,$B$4:$B$203,B14,$AZ$4:$AZ$203,"Да",$BA$4:$BA$203,"Да",$AX$4:$AX$203,"<"&AX14)=0,COUNTIFS($A$4:$A$203,A14,$B$4:$B$203,B14,$AZ$4:$AZ$203,"Да",$BA$4:$BA$203,"Да",$AX$4:$AX$203,"="&AX14,$BF$4:$BF$203,"<"&BF14)=0),"ДА","") | BC14: =IF(AND(AZ14="Да",BA14="Да",COUNTIFS($A$4:$A$203,A14,$B$4:$B$203,B14,$AZ$4:$AZ$203,"Да",$BA$4:$BA$203,"Да",$N$4:$N$203,"<"&N14)=0,COUNTIFS($A$4:$A$203,A14,$B$4:$B$203,B14,$AZ$4:$AZ$203,"Да",$BA$4:$BA$203,"Да",$N$4:$N$203,"="&N14,$BF$4:$BF$203,"<"&BF14)=0),"ДА","") | BD14: =IF(AND(AZ14="Да",BA14="Да",COUNTIFS($A$4:$A$203,A14,$B$4:$B$203,B14,$AZ$4:$AZ$203,"Да",$BA$4:$BA$203,"Да",$AY$4:$AY$203,"<"&AY14)=0,COUNTIFS($A$4:$A$203,A14,$B$4:$B$203,B14,$AZ$4:$AZ$203,"Да",$BA$4:$BA$203,"Да",$AY$4:$AY$203,"="&AY14,$BF$4:$BF$203,"<"&BF14)=0),"ДА","") | BE14: =IF(A14="","",IF(BZ14<>"ПОЛНО","BLOCK: неполная форма",IF(O14<>"Да","BLOCK: ввоз не разрешён",IF(P14<>"Да","BLOCK: документы не подтверждены",IF(ABS(AN14-1)>'03_Настройки'!$B$5,"BLOCK: платежи не 100%",IF(AND(BM14<>"",BM14<>"Активна"),"BLOCK: позиция "&BM14,IF(BA14<>"Да","PARTIAL: не покрывает потребность",IF(BB14="ДА","самый дешёвый"&IF(BC14="ДА"," + быстрый","")&IF(BD14="ДА"," + optimal",""),IF(BC14="ДА","самый быстрый"&IF(BD14="ДА"," + optimal",""),IF(BD14="ДА","optimal","Допущен")))))))))) | BF14: =ROW() -> 14 | BN14: =IF(BG14+BH14=0,"",IF(BG14+BH14<>D14,"⚠ SIM+eSIM≠Доступно","OK")) | BO14: =IF($C14="","",IF(TRIM(IF(O14<>"Да","⚠Ввоз ","")&IF(P14<>"Да","⚠Документы ","")&IF(AND(BG14+BH14>0,D14>0,BG14+BH14<>D14),"⚠SIM/eSIM ","")&IF(BZ14<>"ПОЛНО","⚠НеполнаяФорма ",""))="","OK",TRIM(IF(O14<>"Да","⚠Ввоз ","")&IF(P14<>"Да","⚠Документы ","")&IF(AND(BG14+BH14>0,D14>0,BG14+BH14<>D14),"⚠SIM/eSIM ","")&IF(BZ14<>"ПОЛНО","⚠НеполнаяФорма ","")))) | BX14: =IF(OR(BV14<>"",BW14<>""),"Да","") | BZ14: =IF(A14="","",IF(AND(BT14<>"",BJ14<>"",CA14<>"",BK14<>"",OR(BG14<>"",BH14<>""),BM14<>""),"ПОЛНО","НЕПОЛНО"))
H15: =IFERROR(VLOOKUP(C15,'01_Поставщики'!$A$4:$M$11,2,FALSE()),"") | J15: =IFERROR(VLOOKUP(C15,'01_Поставщики'!$A$4:$M$11,8,FALSE()),"") | K15: =IFERROR(VLOOKUP(C15,'01_Поставщики'!$A$4:$M$11,4,FALSE()),"") | L15: =IFERROR(VLOOKUP(C15,'01_Поставщики'!$A$4:$M$11,10,FALSE()),"") | M15: =IF(OR(A15="",B15=""),"",IFERROR(SUMIFS('04_Потребность'!$B$4:$B$103,'04_Потребность'!$A$4:$A$103,A15,'04_Потребность'!$C$4:$C$103,B15),0)) | T15: =IFERROR(INDEX('02_Схемы оплаты'!$C$4:$C$19,MATCH($C15&"|"&$G15,'02_Схемы оплаты'!$H$4:$H$19,0)),0) -> 0 | X15: =IFERROR(INDEX('02_Схемы оплаты'!$D$4:$D$19,MATCH($C15&"|"&$G15,'02_Схемы оплаты'!$H$4:$H$19,0)),0) -> 0 | AB15: =IFERROR(INDEX('02_Схемы оплаты'!$E$4:$E$19,MATCH($C15&"|"&$G15,'02_Схемы оплаты'!$H$4:$H$19,0)),0) -> 0 | AH15: =IFERROR(SUMIFS('04_Потребность'!$D$4:$D$103,'04_Потребность'!$A$4:$A$103,A15,'04_Потребность'!$C$4:$C$103,B15),0) -> 0 | AI15: =IF(OR(A15="",B15=""),"",IFERROR(SUMIFS('04_Потребность'!$E$4:$E$103,'04_Потребность'!$A$4:$A$103,A15,'04_Потребность'!$C$4:$C$103,B15),0)) | AJ15: =IF(OR(A15="",B15=""),"",IFERROR(SUMIFS('04_Потребность'!$F$4:$F$103,'04_Потребность'!$A$4:$A$103,A15,'04_Потребность'!$C$4:$C$103,B15),0)) | AK15: =IF(OR(A15="",B15=""),"",IFERROR(SUMIFS('04_Потребность'!$G$4:$G$103,'04_Потребность'!$A$4:$A$103,A15,'04_Потребность'!$C$4:$C$103,B15),0)) | AL15: =IF('03_Настройки'!$B$7="Нет","Нет",IF(COUNTIFS('04_Потребность'!$A$4:$A$103,A15,'04_Потребность'!$C$4:$C$103,B15,'04_Потребность'!$H$4:$H$103,"Да")>0,"Да","Нет")) -> Нет | AM15: =IFERROR(MIN(1,D15/AH15),0) -> 0 | AN15: =SUM(T15,X15,AB15) -> 0 | AO15: =IFERROR(E15*(T15*V15*(1+W15)+X15*Z15*(1+AA15)+AB15*AD15*(1+AE15)),0) -> 0 | AP15: =AO15*S15 -> 0 | AQ15: =AO15+AP15+Q15+R15 -> 0 | AR15: =IFERROR(E15*'03_Настройки'!$B$4/365*(IF(T15>0,T15*V15*(1+W15)*MAX(0,N15-U15),0)+IF(X15>0,X15*Z15*(1+AA15)*MAX(0,N15-Y15),0)+IF(AB15>0,AB15*AD15*(1+AE15)*MAX(0,N15-AC15),0)),0) -> 0 | AS15: =AQ15+AR15 -> 0 | AT15: =IFERROR(MAX(0,N15-M15),0) -> 0 | AU15: =IFERROR(MAX(0,N15-AI15),0) -> 0 | AV15: =IF(AL15="Да",MIN(AH15,AJ15*AU15),0) -> 0 | AW15: =AV15*AK15 -> #VALUE! | AX15: =AS15*AH15 -> 0 | AY15: =AX15+AW15 -> #VALUE! | AZ15: =IF(AND(A15<>"",B15<>"",C15<>"",D15>0,E15>0,N15<>"",AH15>0,O15="Да",P15="Да",BZ15="ПОЛНО",ABS(AN15-1)<='03_Настройки'!$B$5,IF(T15>0,AND(U15<>"",V15>0),TRUE()),IF(X15>0,AND(Y15<>"",Z15>0),TRUE()),IF(AB15>0,AND(AC15<>"",AD15>0),TRUE()),OR(BM15="",BM15="Активна")),"Да","Нет") -> Нет | BA15: =IF(AM15>=1,"Да","Нет") -> Нет | BB15: =IF(AND(AZ15="Да",BA15="Да",COUNTIFS($A$4:$A$203,A15,$B$4:$B$203,B15,$AZ$4:$AZ$203,"Да",$BA$4:$BA$203,"Да",$AX$4:$AX$203,"<"&AX15)=0,COUNTIFS($A$4:$A$203,A15,$B$4:$B$203,B15,$AZ$4:$AZ$203,"Да",$BA$4:$BA$203,"Да",$AX$4:$AX$203,"="&AX15,$BF$4:$BF$203,"<"&BF15)=0),"ДА","") | BC15: =IF(AND(AZ15="Да",BA15="Да",COUNTIFS($A$4:$A$203,A15,$B$4:$B$203,B15,$AZ$4:$AZ$203,"Да",$BA$4:$BA$203,"Да",$N$4:$N$203,"<"&N15)=0,COUNTIFS($A$4:$A$203,A15,$B$4:$B$203,B15,$AZ$4:$AZ$203,"Да",$BA$4:$BA$203,"Да",$N$4:$N$203,"="&N15,$BF$4:$BF$203,"<"&BF15)=0),"ДА","") | BD15: =IF(AND(AZ15="Да",BA15="Да",COUNTIFS($A$4:$A$203,A15,$B$4:$B$203,B15,$AZ$4:$AZ$203,"Да",$BA$4:$BA$203,"Да",$AY$4:$AY$203,"<"&AY15)=0,COUNTIFS($A$4:$A$203,A15,$B$4:$B$203,B15,$AZ$4:$AZ$203,"Да",$BA$4:$BA$203,"Да",$AY$4:$AY$203,"="&AY15,$BF$4:$BF$203,"<"&BF15)=0),"ДА","") | BE15: =IF(A15="","",IF(BZ15<>"ПОЛНО","BLOCK: неполная форма",IF(O15<>"Да","BLOCK: ввоз не разрешён",IF(P15<>"Да","BLOCK: документы не подтверждены",IF(ABS(AN15-1)>'03_Настройки'!$B$5,"BLOCK: платежи не 100%",IF(AND(BM15<>"",BM15<>"Активна"),"BLOCK: позиция "&BM15,IF(BA15<>"Да","PARTIAL: не покрывает потребность",IF(BB15="ДА","самый дешёвый"&IF(BC15="ДА"," + быстрый","")&IF(BD15="ДА"," + optimal",""),IF(BC15="ДА","самый быстрый"&IF(BD15="ДА"," + optimal",""),IF(BD15="ДА","optimal","Допущен")))))))))) | BF15: =ROW() -> 15 | BN15: =IF(BG15+BH15=0,"",IF(BG15+BH15<>D15,"⚠ SIM+eSIM≠Доступно","OK")) | BO15: =IF($C15="","",IF(TRIM(IF(O15<>"Да","⚠Ввоз ","")&IF(P15<>"Да","⚠Документы ","")&IF(AND(BG15+BH15>0,D15>0,BG15+BH15<>D15),"⚠SIM/eSIM ","")&IF(BZ15<>"ПОЛНО","⚠НеполнаяФорма ",""))="","OK",TRIM(IF(O15<>"Да","⚠Ввоз ","")&IF(P15<>"Да","⚠Документы ","")&IF(AND(BG15+BH15>0,D15>0,BG15+BH15<>D15),"⚠SIM/eSIM ","")&IF(BZ15<>"ПОЛНО","⚠НеполнаяФорма ","")))) | BX15: =IF(OR(BV15<>"",BW15<>""),"Да","") | BZ15: =IF(A15="","",IF(AND(BT15<>"",BJ15<>"",CA15<>"",BK15<>"",OR(BG15<>"",BH15<>""),BM15<>""),"ПОЛНО","НЕПОЛНО"))
H16: =IFERROR(VLOOKUP(C16,'01_Поставщики'!$A$4:$M$11,2,FALSE()),"") | J16: =IFERROR(VLOOKUP(C16,'01_Поставщики'!$A$4:$M$11,8,FALSE()),"") | K16: =IFERROR(VLOOKUP(C16,'01_Поставщики'!$A$4:$M$11,4,FALSE()),"") | L16: =IFERROR(VLOOKUP(C16,'01_Поставщики'!$A$4:$M$11,10,FALSE()),"") | M16: =IF(OR(A16="",B16=""),"",IFERROR(SUMIFS('04_Потребность'!$B$4:$B$103,'04_Потребность'!$A$4:$A$103,A16,'04_Потребность'!$C$4:$C$103,B16),0)) | T16: =IFERROR(INDEX('02_Схемы оплаты'!$C$4:$C$19,MATCH($C16&"|"&$G16,'02_Схемы оплаты'!$H$4:$H$19,0)),0) -> 0 | X16: =IFERROR(INDEX('02_Схемы оплаты'!$D$4:$D$19,MATCH($C16&"|"&$G16,'02_Схемы оплаты'!$H$4:$H$19,0)),0) -> 0 | AB16: =IFERROR(INDEX('02_Схемы оплаты'!$E$4:$E$19,MATCH($C16&"|"&$G16,'02_Схемы оплаты'!$H$4:$H$19,0)),0) -> 0 | AH16: =IFERROR(SUMIFS('04_Потребность'!$D$4:$D$103,'04_Потребность'!$A$4:$A$103,A16,'04_Потребность'!$C$4:$C$103,B16),0) -> 0 | AI16: =IF(OR(A16="",B16=""),"",IFERROR(SUMIFS('04_Потребность'!$E$4:$E$103,'04_Потребность'!$A$4:$A$103,A16,'04_Потребность'!$C$4:$C$103,B16),0)) | AJ16: =IF(OR(A16="",B16=""),"",IFERROR(SUMIFS('04_Потребность'!$F$4:$F$103,'04_Потребность'!$A$4:$A$103,A16,'04_Потребность'!$C$4:$C$103,B16),0)) | AK16: =IF(OR(A16="",B16=""),"",IFERROR(SUMIFS('04_Потребность'!$G$4:$G$103,'04_Потребность'!$A$4:$A$103,A16,'04_Потребность'!$C$4:$C$103,B16),0)) | AL16: =IF('03_Настройки'!$B$7="Нет","Нет",IF(COUNTIFS('04_Потребность'!$A$4:$A$103,A16,'04_Потребность'!$C$4:$C$103,B16,'04_Потребность'!$H$4:$H$103,"Да")>0,"Да","Нет")) -> Нет | AM16: =IFERROR(MIN(1,D16/AH16),0) -> 0 | AN16: =SUM(T16,X16,AB16) -> 0 | AO16: =IFERROR(E16*(T16*V16*(1+W16)+X16*Z16*(1+AA16)+AB16*AD16*(1+AE16)),0) -> 0 | AP16: =AO16*S16 -> 0 | AQ16: =AO16+AP16+Q16+R16 -> 0 | AR16: =IFERROR(E16*'03_Настройки'!$B$4/365*(IF(T16>0,T16*V16*(1+W16)*MAX(0,N16-U16),0)+IF(X16>0,X16*Z16*(1+AA16)*MAX(0,N16-Y16),0)+IF(AB16>0,AB16*AD16*(1+AE16)*MAX(0,N16-AC16),0)),0) -> 0 | AS16: =AQ16+AR16 -> 0 | AT16: =IFERROR(MAX(0,N16-M16),0) -> 0 | AU16: =IFERROR(MAX(0,N16-AI16),0) -> 0 | AV16: =IF(AL16="Да",MIN(AH16,AJ16*AU16),0) -> 0 | AW16: =AV16*AK16 -> #VALUE! | AX16: =AS16*AH16 -> 0 | AY16: =AX16+AW16 -> #VALUE! | AZ16: =IF(AND(A16<>"",B16<>"",C16<>"",D16>0,E16>0,N16<>"",AH16>0,O16="Да",P16="Да",BZ16="ПОЛНО",ABS(AN16-1)<='03_Настройки'!$B$5,IF(T16>0,AND(U16<>"",V16>0),TRUE()),IF(X16>0,AND(Y16<>"",Z16>0),TRUE()),IF(AB16>0,AND(AC16<>"",AD16>0),TRUE()),OR(BM16="",BM16="Активна")),"Да","Нет") -> Нет | BA16: =IF(AM16>=1,"Да","Нет") -> Нет | BB16: =IF(AND(AZ16="Да",BA16="Да",COUNTIFS($A$4:$A$203,A16,$B$4:$B$203,B16,$AZ$4:$AZ$203,"Да",$BA$4:$BA$203,"Да",$AX$4:$AX$203,"<"&AX16)=0,COUNTIFS($A$4:$A$203,A16,$B$4:$B$203,B16,$AZ$4:$AZ$203,"Да",$BA$4:$BA$203,"Да",$AX$4:$AX$203,"="&AX16,$BF$4:$BF$203,"<"&BF16)=0),"ДА","") | BC16: =IF(AND(AZ16="Да",BA16="Да",COUNTIFS($A$4:$A$203,A16,$B$4:$B$203,B16,$AZ$4:$AZ$203,"Да",$BA$4:$BA$203,"Да",$N$4:$N$203,"<"&N16)=0,COUNTIFS($A$4:$A$203,A16,$B$4:$B$203,B16,$AZ$4:$AZ$203,"Да",$BA$4:$BA$203,"Да",$N$4:$N$203,"="&N16,$BF$4:$BF$203,"<"&BF16)=0),"ДА","") | BD16: =IF(AND(AZ16="Да",BA16="Да",COUNTIFS($A$4:$A$203,A16,$B$4:$B$203,B16,$AZ$4:$AZ$203,"Да",$BA$4:$BA$203,"Да",$AY$4:$AY$203,"<"&AY16)=0,COUNTIFS($A$4:$A$203,A16,$B$4:$B$203,B16,$AZ$4:$AZ$203,"Да",$BA$4:$BA$203,"Да",$AY$4:$AY$203,"="&AY16,$BF$4:$BF$203,"<"&BF16)=0),"ДА","") | BE16: =IF(A16="","",IF(BZ16<>"ПОЛНО","BLOCK: неполная форма",IF(O16<>"Да","BLOCK: ввоз не разрешён",IF(P16<>"Да","BLOCK: документы не подтверждены",IF(ABS(AN16-1)>'03_Настройки'!$B$5,"BLOCK: платежи не 100%",IF(AND(BM16<>"",BM16<>"Активна"),"BLOCK: позиция "&BM16,IF(BA16<>"Да","PARTIAL: не покрывает потребность",IF(BB16="ДА","самый дешёвый"&IF(BC16="ДА"," + быстрый","")&IF(BD16="ДА"," + optimal",""),IF(BC16="ДА","самый быстрый"&IF(BD16="ДА"," + optimal",""),IF(BD16="ДА","optimal","Допущен")))))))))) | BF16: =ROW() -> 16 | BN16: =IF(BG16+BH16=0,"",IF(BG16+BH16<>D16,"⚠ SIM+eSIM≠Доступно","OK")) | BO16: =IF($C16="","",IF(TRIM(IF(O16<>"Да","⚠Ввоз ","")&IF(P16<>"Да","⚠Документы ","")&IF(AND(BG16+BH16>0,D16>0,BG16+BH16<>D16),"⚠SIM/eSIM ","")&IF(BZ16<>"ПОЛНО","⚠НеполнаяФорма ",""))="","OK",TRIM(IF(O16<>"Да","⚠Ввоз ","")&IF(P16<>"Да","⚠Документы ","")&IF(AND(BG16+BH16>0,D16>0,BG16+BH16<>D16),"⚠SIM/eSIM ","")&IF(BZ16<>"ПОЛНО","⚠НеполнаяФорма ","")))) | BX16: =IF(OR(BV16<>"",BW16<>""),"Да","") | BZ16: =IF(A16="","",IF(AND(BT16<>"",BJ16<>"",CA16<>"",BK16<>"",OR(BG16<>"",BH16<>""),BM16<>""),"ПОЛНО","НЕПОЛНО"))
... H203: =IFERROR(VLOOKUP(C203,'01_Поставщики'!$A$4:$M$11,2,FALSE()),"") | J203: =IFERROR(VLOOKUP(C203,'01_Поставщики'!$A$4:$M$11,8,FALSE()),"") | K203: =IFERROR(VLOOKUP(C203,'01_Поставщики'!$A$4:$M$11,4,FALSE()),"") | L203: =IFERROR(VLOOKUP(C203,'01_Поставщики'!$A$4:$M$11,10,FALSE()),"") | M203: =IF(OR(A203="",B203=""),"",IFERROR(SUMIFS('04_Потребность'!$B$4:$B$103,'04_Потребность'!$A$4:$A$103,A203,'04_Потребность'!$C$4:$C$103,B203),0)) | T203: =IFERROR(INDEX('02_Схемы оплаты'!$C$4:$C$19,MATCH($C203&"|"&$G203,'02_Схемы оплаты'!$H$4:$H$19,0)),0) -> 0 | X203: =IFERROR(INDEX('02_Схемы оплаты'!$D$4:$D$19,MATCH($C203&"|"&$G203,'02_Схемы оплаты'!$H$4:$H$19,0)),0) -> 0 | AB203: =IFERROR(INDEX('02_Схемы оплаты'!$E$4:$E$19,MATCH($C203&"|"&$G203,'02_Схемы оплаты'!$H$4:$H$19,0)),0) -> 0 | AH203: =IFERROR(SUMIFS('04_Потребность'!$D$4:$D$103,'04_Потребность'!$A$4:$A$103,A203,'04_Потребность'!$C$4:$C$103,B203),0) -> 0 | AI203: =IF(OR(A203="",B203=""),"",IFERROR(SUMIFS('04_Потребность'!$E$4:$E$103,'04_Потребность'!$A$4:$A$103,A203,'04_Потребность'!$C$4:$C$103,B203),0)) | AJ203: =IF(OR(A203="",B203=""),"",IFERROR(SUMIFS('04_Потребность'!$F$4:$F$103,'04_Потребность'!$A$4:$A$103,A203,'04_Потребность'!$C$4:$C$103,B203),0)) | AK203: =IF(OR(A203="",B203=""),"",IFERROR(SUMIFS('04_Потребность'!$G$4:$G$103,'04_Потребность'!$A$4:$A$103,A203,'04_Потребность'!$C$4:$C$103,B203),0)) | AL203: =IF('03_Настройки'!$B$7="Нет","Нет",IF(COUNTIFS('04_Потребность'!$A$4:$A$103,A203,'04_Потребность'!$C$4:$C$103,B203,'04_Потребность'!$H$4:$H$103,"Да")>0,"Да","Нет")) -> Нет | AM203: =IFERROR(MIN(1,D203/AH203),0) -> 0 | AN203: =SUM(T203,X203,AB203) -> 0 | AO203: =IFERROR(E203*(T203*V203*(1+W203)+X203*Z203*(1+AA203)+AB203*AD203*(1+AE203)),0) -> 0 | AP203: =AO203*S203 -> 0 | AQ203: =AO203+AP203+Q203+R203 -> 0 | AR203: =IFERROR(E203*'03_Настройки'!$B$4/365*(IF(T203>0,T203*V203*(1+W203)*MAX(0,N203-U203),0)+IF(X203>0,X203*Z203*(1+AA203)*MAX(0,N203-Y203),0)+IF(AB203>0,AB203*AD203*(1+AE203)*MAX(0,N203-AC203),0)),0) -> 0 | AS203: =AQ203+AR203 -> 0 | AT203: =IFERROR(MAX(0,N203-M203),0) -> 0 | AU203: =IFERROR(MAX(0,N203-AI203),0) -> 0 | AV203: =IF(AL203="Да",MIN(AH203,AJ203*AU203),0) -> 0 | AW203: =AV203*AK203 -> #VALUE! | AX203: =AS203*AH203 -> 0 | AY203: =AX203+AW203 -> #VALUE! | AZ203: =IF(AND(A203<>"",B203<>"",C203<>"",D203>0,E203>0,N203<>"",AH203>0,O203="Да",P203="Да",BZ203="ПОЛНО",ABS(AN203-1)<='03_Настройки'!$B$5,IF(T203>0,AND(U203<>"",V203>0),TRUE()),IF(X203>0,AND(Y203<>"",Z203>0),TRUE()),IF(AB203>0,AND(AC203<>"",AD203>0),TRUE()),OR(BM203="",BM203="Активна")),"Да","Нет") -> Нет | BA203: =IF(AM203>=1,"Да","Нет") -> Нет | BB203: =IF(AND(AZ203="Да",BA203="Да",COUNTIFS($A$4:$A$203,A203,$B$4:$B$203,B203,$AZ$4:$AZ$203,"Да",$BA$4:$BA$203,"Да",$AX$4:$AX$203,"<"&AX203)=0,COUNTIFS($A$4:$A$203,A203,$B$4:$B$203,B203,$AZ$4:$AZ$203,"Да",$BA$4:$BA$203,"Да",$AX$4:$AX$203,"="&AX203,$BF$4:$BF$203,"<"&BF203)=0),"ДА","") | BC203: =IF(AND(AZ203="Да",BA203="Да",COUNTIFS($A$4:$A$203,A203,$B$4:$B$203,B203,$AZ$4:$AZ$203,"Да",$BA$4:$BA$203,"Да",$N$4:$N$203,"<"&N203)=0,COUNTIFS($A$4:$A$203,A203,$B$4:$B$203,B203,$AZ$4:$AZ$203,"Да",$BA$4:$BA$203,"Да",$N$4:$N$203,"="&N203,$BF$4:$BF$203,"<"&BF203)=0),"ДА","") | BD203: =IF(AND(AZ203="Да",BA203="Да",COUNTIFS($A$4:$A$203,A203,$B$4:$B$203,B203,$AZ$4:$AZ$203,"Да",$BA$4:$BA$203,"Да",$AY$4:$AY$203,"<"&AY203)=0,COUNTIFS($A$4:$A$203,A203,$B$4:$B$203,B203,$AZ$4:$AZ$203,"Да",$BA$4:$BA$203,"Да",$AY$4:$AY$203,"="&AY203,$BF$4:$BF$203,"<"&BF203)=0),"ДА","") | BE203: =IF(A203="","",IF(BZ203<>"ПОЛНО","BLOCK: неполная форма",IF(O203<>"Да","BLOCK: ввоз не разрешён",IF(P203<>"Да","BLOCK: документы не подтверждены",IF(ABS(AN203-1)>'03_Настройки'!$B$5,"BLOCK: платежи не 100%",IF(AND(BM203<>"",BM203<>"Активна"),"BLOCK: позиция "&BM203,IF(BA203<>"Да","PARTIAL: не покрывает потребность",IF(BB203="ДА","самый дешёвый"&IF(BC203="ДА"," + быстрый","")&IF(BD203="ДА"," + optimal",""),IF(BC203="ДА","самый быстрый"&IF(BD203="ДА"," + optimal",""),IF(BD203="ДА","optimal","Допущен")))))))))) | BF203: =ROW() -> 203 | BN203: =IF(BG203+BH203=0,"",IF(BG203+BH203<>D203,"⚠ SIM+eSIM≠Доступно","OK")) | BO203: =IF($C203="","",IF(TRIM(IF(O203<>"Да","⚠Ввоз ","")&IF(P203<>"Да","⚠Документы ","")&IF(AND(BG203+BH203>0,D203>0,BG203+BH203<>D203),"⚠SIM/eSIM ","")&IF(BZ203<>"ПОЛНО","⚠НеполнаяФорма ",""))="","OK",TRIM(IF(O203<>"Да","⚠Ввоз ","")&IF(P203<>"Да","⚠Документы ","")&IF(AND(BG203+BH203>0,D203>0,BG203+BH203<>D203),"⚠SIM/eSIM ","")&IF(BZ203<>"ПОЛНО","⚠НеполнаяФорма ","")))) | BX203: =IF(OR(BV203<>"",BW203<>""),"Да","") | BZ203: =IF(A203="","",IF(AND(BT203<>"",BJ203<>"",CA203<>"",BK203<>"",OR(BG203<>"",BH203<>""),BM203<>""),"ПОЛНО","НЕПОЛНО"))

Sheet 00_Панель
A1: ТЕНДЕРНЫЙ КАЛЬКУЛЯТОР APPLE — панель решения
A3: Выбор для просмотра
A4: Tender ID
A5: SKU / Артикул Patio
A6: Потребность, шт | B6: =IFERROR(SUMIFS('04_Потребность'!$D$4:$D$103,'04_Потребность'!$A$4:$A$103,B4,'04_Потребность'!$C$4:$C$103,B5),0) -> 0
A7: Нужная дата ЦС | B7: =IFERROR(_xlfn.MAXIFS('04_Потребность'!$E$4:$E$103,'04_Потребность'!$A$4:$A$103,B4,'04_Потребность'!$C$4:$C$103,B5),"")
A8: Статус | B8: =IF(B6=0,"Нет потребности",IF(COUNTIFS('05_Офферы'!$A$4:$A$203,B4,'05_Офферы'!$B$4:$B$203,B5,'05_Офферы'!$AZ$4:$AZ$203,"Да",'05_Офферы'!$BA$4:$BA$203,"Да")>0,"ГОТОВО",IF(COUNTIFS('05_Офферы'!$A$4:$A$203,B4,'05_Офферы'!$B$4:$B$203,B5,'05_Офферы'!$AZ$4:$AZ$203,"Да")>0,"Есть допущенные, но нет полного покрытия","Нет допущенных офферов"))) -> Нет потребности
A10: Результат | B10: Поставщик | C10: Значение | D10: Логика | F10: Результат | G10: Строка | H10: Риск
A11: Самый дешёвый | B11: =IF($G11=0,"",INDEX('05_Офферы'!$C:$C,$G11)) | C11: =IF($G11=0,"",INDEX('05_Офферы'!$AX:$AX,$G11)) | D11: Минимальная полная финансовая стоимость закупки | F11: CHEAPEST | G11: =IFERROR(SUMIFS('05_Офферы'!$BF$4:$BF$203,'05_Офферы'!$A$4:$A$203,$B$4,'05_Офферы'!$B$4:$B$203,$B$5,'05_Офферы'!$BB$4:$BB$203,"ДА"),0) -> 0 | H11: =IF($G11=0,"",INDEX('05_Офферы'!$AF:$AF,$G11))
A12: Самый быстрый | B12: =IF($G12=0,"",INDEX('05_Офферы'!$C:$C,$G12)) | C12: =IF($G12=0,"",INDEX('05_Офферы'!$N:$N,$G12)) | D12: Минимальная ETA на ЦС | F12: FASTEST | G12: =IFERROR(SUMIFS('05_Офферы'!$BF$4:$BF$203,'05_Офферы'!$A$4:$A$203,$B$4,'05_Офферы'!$B$4:$B$203,$B$5,'05_Офферы'!$BC$4:$BC$203,"ДА"),0) -> 0 | H12: =IF($G12=0,"",INDEX('05_Офферы'!$AF:$AF,$G12))
A13: Оптимальный | B13: =IF($G13=0,"",INDEX('05_Офферы'!$C:$C,$G13)) | C13: =IF($G13=0,"",INDEX('05_Офферы'!$AY:$AY,$G13)) | D13: Минимальная экономическая стоимость = закупка + потери от дефицита | F13: OPTIMAL | G13: =IFERROR(SUMIFS('05_Офферы'!$BF$4:$BF$203,'05_Офферы'!$A$4:$A$203,$B$4,'05_Офферы'!$B$4:$B$203,$B$5,'05_Офферы'!$BD$4:$BD$203,"ДА"),0) -> 0 | H13: =IF($G13=0,"",INDEX('05_Офферы'!$AF:$AF,$G13))
A16: Как считается Optimal
A17: Optimal не использует субъективные веса цены и скорости. Он переводит опоздание в деньги: потерянные продажи = min(потребность; продажи/день × дни опоздания), потери ВП = потерянные продажи × маржа/ед. Затем сравнивается стоимость закупки + потери ВП. Если расчёт дефицита отключён — Optimal совпадает с самым дешёвым вариантом.
A22: Ключевой принцип
A23: ДОПУСК → ЭКОНОМИКА → РЕШЕНИЕ. Оффер не участвует в сравнении (Cheapest/Fastest/Optimal), пока не раскрыты все критические данные, ввоз не разрешён Patio, документы/нотификация не подтверждены (или прямо помечены «не требуется»), а доли платежей не сходятся к 100%. Цена и скорость не компенсируют отсутствие данных или несоблюдение хард-стопов — такой оффер получает BLOCK и не ранжируется, а не «худший, но допущенный» результат.

Sheet 06_Методика
A1: Методика расчёта — контрольная карта
A3: № | B3: Показатель | C3: Формула / правило | D3: Зачем | E3: Примечание
A4: 1 | B4: Стоимость товара/ед. | C4: Цена × Σ(доля платежа × курс платежа × (1+комиссия платежа)) | D4: Учитывает разные даты/курсы/комиссии по траншам | E4: Ключевой принцип
A5: 2 | B5: Cash landed/ед. | C5: Товар + страхование + логистика + прочие расходы | D5: Цена на ЦС до стоимости денег | E5: Не дублировать расходы, уже включённые в базис
A6: 3 | B6: Стоимость денег | C6: Σ(сумма транша × 13% × max(0; ETA−дата платежа)/365) | D6: Цена предоплаты и замороженных денег | E6: Отсрочка после ETA не получает отрицательный бонус
A7: 4 | B7: Полная фин. цена/ед. | C7: Cash landed + стоимость денег | D7: Основа CHEAPEST
A8: 5 | B8: Покрытие | C8: min(1; доступно/потребность) | D8: Контроль частичных офферов | E8: Частичный оффер не может быть единственным победителем MVP
A9: 6 | B9: Опоздание | C9: max(0; ETA−нужная дата ЦС) | D9: Связь скорости и экономики
A10: 7 | B10: Потерянные продажи | C10: min(потребность; продажи/день × опоздание) | D10: Монетизация дефицита | E10: Только при включённом расчёте дефицита
A11: 8 | B11: Потери ВП | C11: потерянные продажи × маржа/ед. | D11: Стоимость опоздания
A12: 9 | B12: Стоимость закупки | C12: полная фин. цена/ед. × потребность | D12: Сравнение офферов на одинаковом объёме | E12: Только полное покрытие
A13: 10 | B13: Экономическая стоимость | C13: стоимость закупки + потери ВП | D13: Основа OPTIMAL
A14: 11 | B14: CHEAPEST | C14: минимальная стоимость закупки среди допустимых офферов с полным покрытием | D14: Результат
A15: 12 | B15: FASTEST | C15: минимальная ETA среди допустимых офферов с полным покрытием | D15: Результат
A16: 13 | B16: OPTIMAL | C16: минимальная экономическая стоимость среди допустимых офферов с полным покрытием | D16: Результат | E16: Без субъективных весов цены/скорости
A17: 14 | B17: Hard stop | C17: ввоз ≠ Да; документы ≠ Да; доли платежей ≠100%; нет цены/ETA/курса/дат | D17: Исключение ошибочного победителя
A18: 15 | B18: Схема оплаты | C18: Доли платежей 1/2/3 подтягиваются автоматически по ключу «Поставщик|Схема» из листа «02_Схемы оплаты»; КМ может вручную переписать %, если нужна нестандартная разбивка | D18: Меньше ручного ввода и ошибок в процентах | E18: Правки в T/X/AB допустимы — формула просто перезаписывается значением
A19: 16 | B19: Статус позиции | C19: Если «Статус позиции» = Приостановлена/Отменена — оффер не может стать победителем (аналог отмены строки без порчи данных) | D19: Замена текстового хака «отмена!!!!» из старой формы | E19: Пусто = считается Активна
A20: 17 | B20: Флаг соответствия | C20: ⚠Ввоз / ⚠Документы / ⚠Нотификация / ⚠SIM/eSIM / ⚠СертИстёк / ⚠НетСерт№, иначе OK | D20: Автоматическое выявление ограничений по импорту/сертификации без ручной проверки | E20: Не блокирует расчёт сам по себе (кроме Ввоз/Документы, которые уже блокируют через AZ) — это сигнал для КМ, что нужно уточнить у поставщика
A21: 18 | B21: Полнота формы | C21: Срок оффера, named place, логистика, рынок, A-number, происхождение, SIM/eSIM и документы | D21: Hard stop | E21: Цена не компенсирует неполный ответ
A22: 19 | B22: Замена | C22: Если поставщик предлагает отличие, требуется отдельное согласование Patio | D22: Hard stop | E22: Другой товар не сравнивается как исходный SKU
A23: 20 | B23: Совместимость | C23: Победители COUNTIFS; панель SUMIFS; статусы без TEXTJOIN | D23: Техническая устойчивость | E23: Нет MINIFS/MAXIFS/TEXTJOIN
A24: 21 | B24: Срок оффера | C24: Оффер должен быть действителен на дату расчёта | D24: Hard stop | E24: Просроченная цена не участвует
A25: 22 | B25: Форма | C25: Калькулятор принимает текущую рабочую форму с минимальными изменениями | D25: Основной интерфейс КМ | E25: Форма не подстраивается под движок
A26: 23 | B26: Минимальные изменения | C26: Единая потребность; нужная дата ЦС; статус позиции; ясная цепочка цены; модель/код; сертификат; цветовое разделение ролей | D26: Без перестройки процесса | E26: Сохранена привычная форма

Sheet 07_Проверка
A1: Контроль перед использованием результата тендера
A3: № | B3: Проверка | C3: Что должно быть | D3: Критично
A4: 1 | B4: Потребность | C4: Для Tender ID + SKU заполнены дата тендера, количество и нужная дата | D4: Да
A5: 2 | B5: Цена | C5: Цена и валюта оффера заполнены | D5: Да
A6: 3 | B6: Платежи | C6: Сумма долей = 100%; для каждого активного транша есть дата и курс | D6: Да
A7: 4 | B7: Комиссии | C7: Комиссия задана именно на том платеже, к которому реально применяется | D7: Да
A8: 5 | B8: Логистика | C8: Введены только расходы, не включённые уже в базис/цену | D8: Да
A9: 6 | B9: ETA | C9: Указана дата прихода именно на ЦС Минск | D9: Да
A10: 7 | B10: Документы | C10: Ввоз разрешён = Да; документы подтверждены = Да | D10: Да
A11: 8 | B11: Дефицит | C11: Продажи/день и маржа заполнены только если их можно обосновать | D11: Да
A12: 9 | B12: Частичный оффер | C12: Не принимать как единственного победителя, если доступно < потребности | D12: Да
A13: 10 | B13: Metal Market | C13: До первых фактических поставок неоднозначные условия вводить вручную | D13: Да
A14: 11 | B14: Схема оплаты | C14: Выбрана схема именно того поставщика, что указан в оффере (иначе доли платежей не подтянутся — будут нули) | D14: Да
A15: 12 | B15: Статус позиции | C15: Отменённые/приостановленные позиции помечены в «Статус позиции», а не текстом в поле цвета/названия | D15: Да
A16: 13 | B16: Соответствие | C16: Столбец «Флаг соответствия» = OK по всем офферам, которые рассматриваются как победители | D16: Да

Sheet 08_Источники
A1: Источники и статус входных данных
A2: Заполняется и обновляется КМ при каждом пересчёте тендера. «Статус» отмечает, можно ли доверять данным как текущим, или они устарели и требуют подтверждения.
A4: Источник | B4: Дата | C4: Как использован | D4: Статус | E4: Комментарий
A5: Свод инфо по Apple-трейдерам (файл КМ) | B5: 18.08.2026 | C5: Справочник условий поставщиков — 01_Поставщики | D5: Свежий источник
A6: Форма заявки поставщику (по каждому тендеру) | B6: заполняется по факту | C6: Строки 05_Офферы — вставка из персикового блока формы | D6: Обновлять на каждый тендер
A7: Потребность / таргет КМ | B7: заполняется по факту | C7: 04_Потребность — количество, нужная дата, продажи/день, маржа | D7: Обновлять на каждый тендер
A8: Курсы валют | B8: заполняется по факту | C8: 03_Настройки — курсы к BYN на дату расчёта | D8: Обновлять на каждый тендер | E8: Не использовать курс старше нескольких дней без проверки
A9: Claude — калькулятор | B9: 20.08.2026 | C9: Сохранены сильные блоки: источники потребности, схемы оплаты, соответствие | D9: Проанализирован | E9: MINIFS/TEXTJOIN заменены
A10: Claude — форма заявки | B10: 20.08.2026 | C10: Сохранены сильные поля: срок оффера, named place, рынок, документы | D10: Проанализирован | E10: Обезличена в финальной форме
A11: Итоговая версия | B11: 20.08.2026 | C11: Единая модель допуска и выбора | D11: Текущая | E11: Без демонстрационных закупочных данных
A12: Текущая рабочая форма Apple/Noviva | B12: 04.08.2026 | C12: Взята как 100% основа пользовательского процесса | D12: Старше 2 недель — структура, не текущие цены/количества
A13: Оптимизированная форма | B13: 20.08.2026 | C13: Минимально скорректирована и состыкована с калькулятором | D13: Текущая версия

Sheet 09_Маппинг формы
A1: Поле текущей формы | B1: Колонка | C1: Поле калькулятора | D1: Куда попадает | E1: Комментарий
A2: Наименование | B2: A | C2: SKU / наименование | D2: 04_Потребность / 05_Офферы | E2: Основная позиция
A3: Цвет | B3: B | C3: Цвет / описание | D3: Комментарий | E3: Не отдельный расчетный ключ
A4: Потребность, шт | B4: C | C4: Потребность | D4: 04_Потребность | E4: Единое поле
A5: Нужная дата на ЦС | B5: D | C5: Нужная дата | D5: 04_Потребность | E5: Небольшое добавление к текущей форме
A6: Статус позиции | B6: E | C6: Статус позиции | D6: 05_Офферы BM | E6: Активна / Нет предложения / Отменена
A7: SIM | B7: F | C7: SIM | D7: 05_Офферы BG
A8: eSIM | B8: G | C8: eSIM | D8: 05_Офферы BH
A9: Возможность к поставке | B9: H | C9: Доступно, шт | D9: 05_Офферы D
A10: Цена поставщика | B10: I | C10: Цена оффера | D10: 05_Офферы E
A11: Таргет КМ | B11: J | C11: Таргет | D11: справочно | E11: Не влияет на рейтинг напрямую
A12: Финальная цена | B12: K | C12: Цена к расчету | D12: 05_Офферы E | E12: Если заполнена — приоритет над первоначальной
A13: Страна производства | B13: L | C13: Страна происхождения | D13: 05_Офферы BT
A14: Нотификация | B14: M | C14: Нотификация | D14: 05_Офферы BJ
A15: Модель / код устройства | B15: N | C15: Модель / A-number | D15: 05_Офферы CA
A16: Сертификат / действующий протокол | B16: O | C16: Документ | D16: 05_Офферы BK / P | E16: Проверка документа — внутренняя
